{
    "A": 8.07276,
    "B": 3.51999,
    "C": 2.56677,
    "Cv": "23.780",
    "G": -196.375854,
    "H": -196.338151,
    "P": 1.0,
    "S": 0.00012645648163673784,
    "T": 298.15,
    "U": -196.339095,
    "U0": -196.345984,
    "alpha": 42.17366666666667,
    "alpha_xx": 80.086,
    "alpha_xy": -5.044,
    "alpha_xz": 62.11,
    "alpha_yy": 0.0,
    "alpha_yz": 0.0,
    "alpha_zz": 46.435,
    "bo": [
        0,
        1,
        0,
        0,
        0,
        1,
        1,
        1,
        0,
        0,
        0,
        0,
        0,
        0,
        0,
        1,
        0,
        2,
        0,
        0,
        0,
        0,
        0,
        1,
        0,
        0,
        0,
        0,
        0,
        0,
        0,
        2,
        0,
        1,
        1,
        0,
        0,
        0,
        0,
        0,
        0,
        0,
        0,
        0,
        0,
        0,
        0,
        1,
        0,
        0,
        0,
        0,
        0,
        0,
        1,
        1,
        1,
        0,
        0,
        0,
        0,
        0,
        1,
        0,
        0,
        0,
        0,
        0,
        0,
        0,
        0,
        0,
        1,
        1,
        1,
        1,
        0,
        0,
        0,
        0,
        0,
        0,
        0,
        0,
        0,
        0,
        0,
        0,
        0,
        0,
        1,
        0,
        0,
        0,
        0,
        0,
        0,
        0,
        0,
        0,
        0,
        0,
        0,
        0,
        0,
        1,
        0,
        0,
        0,
        0,
        0,
        0,
        0,
        0,
        0,
        0,
        0,
        0,
        0,
        0,
        0,
        1,
        0,
        0,
        0,
        0,
        0,
        0,
        0,
        0,
        0,
        0,
        0,
        0,
        0,
        0,
        0,
        0,
        1,
        0,
        0,
        0,
        0,
        0,
        0,
        0,
        0,
        0,
        0,
        0,
        0,
        0,
        0,
        1,
        0,
        0,
        0,
        0,
        0,
        0,
        0,
        0,
        0,
        0,
        0,
        0,
        0,
        0,
        1,
        0,
        0,
        0,
        0,
        0,
        0,
        0,
        0,
        0,
        0,
        0,
        0,
        0,
        0,
        0,
        1,
        0,
        0,
        0,
        0,
        0,
        0,
        0,
        0,
        0,
        0,
        0,
        0,
        0,
        0,
        1,
        0,
        0,
        0,
        0,
        0,
        0,
        0,
        0,
        0,
        0,
        0,
        0,
        0,
        0,
        1,
        0,
        0,
        0,
        0,
        0,
        0,
        0,
        0,
        0,
        0
    ],
    "coords": [
        2.107578,
        -0.075231,
        -4e-06,
        0.731382,
        -0.669519,
        -3e-06,
        -0.447078,
        -0.041934,
        0.0,
        -0.626983,
        1.452105,
        3e-06,
        -1.736149,
        -0.821336,
        2e-06,
        2.106371,
        1.013111,
        3e-06,
        2.673417,
        -0.406399,
        0.875894,
        2.673412,
        -0.406389,
        -0.875908,
        0.710277,
        -1.756374,
        -5e-06,
        0.311866,
        2.000602,
        -1.3e-05,
        -1.20135,
        1.769155,
        -0.87596,
        -1.201321,
        1.769155,
        0.875985,
        -2.34392,
        -0.575385,
        -0.87656,
        -1.560021,
        -1.89668,
        -1e-06,
        -2.343915,
        -0.575389,
        0.876568
    ],
    "e ne": -803.5483248131,
    "e_disp": -0.007725239500018688,
    "e_k": 195.1684653273,
    "e_nn": 174.5828800426,
    "eigs": [
        -10.171459635787112,
        -10.160869636166312,
        -10.160379636183858,
        -10.159219636225396,
        -10.157799636276241,
        -0.8084199710526335,
        -0.7305899738395183,
        -0.6883499753520204,
        -0.6342199772902714,
        -0.5097699817464942,
        -0.45965998354079995,
        -0.43248998451368525,
        -0.4304099845881645,
        -0.40134998562872565,
        -0.3810099863570469,
        -0.37969998640395447,
        -0.3660699868920085,
        -0.35507998728553114,
        -0.32618998832000506,
        -0.2319399916948465,
        0.02710999902926312,
        0.037889998643260044,
        0.062449997763831866,
        0.07475999732304356,
        0.10096999638453329,
        0.10289999631542514,
        0.11069999603612792,
        0.11822999576649866,
        0.14749999471841793,
        0.1484999946826106,
        0.1685799939635993,
        0.1751199937294193,
        0.19940999285965913,
        0.2193999921438705,
        0.2326999916676329,
        0.2578399907674365,
        0.2647499905200078,
        0.2812499899291867,
        0.30670998901753194,
        0.3284899882376482,
        0.3379499878989108,
        0.370509986733024,
        0.37281998665030897,
        0.3805499863735182,
        0.392579985942756,
        0.426929984712774,
        0.44214998416778634,
        0.4469799839948369,
        0.4582399835916463,
        0.46178998346453026,
        0.4697699831787878,
        0.46980998317735545,
        0.48038998279851386,
        0.48238998272689915,
        0.48335998269216607,
        0.4984599821514753,
        0.5263999811510183,
        0.5432399805480227,
        0.5521299802296956,
        0.579469979250723,
        0.5830199791236069,
        0.5937199787404686,
        0.6546799765576533,
        0.6672799761064808,
        0.6977699750147152,
        0.7142199744256844,
        0.745919973290592,
        0.7818299720047505,
        0.7927599716133763,
        0.8365299700460891,
        0.8431599698086866,
        0.8624199691190372,
        0.8681299689145774,
        0.8909199680985282,
        0.9419499662712798,
        0.9423699662562408,
        0.9469499660922431,
        0.9505699659626207,
        0.9700699652643776,
        0.9928699644479703,
        1.0033399640730674,
        1.0191499635069534,
        1.0305699630980338,
        1.0527499623038272,
        1.0623799619590024,
        1.0652599618558773,
        1.0828099612274587,
        1.117659959979573,
        1.1246899597278472,
        1.154839958648256,
        1.1752599579170702,
        1.1833299576281051,
        1.2083899567307732,
        1.2221599562377061,
        1.2470599553461035,
        1.2820799540921308,
        1.2852599539782634,
        1.3079099531672271,
        1.310079953089525,
        1.3295199523934307,
        1.333579952248053,
        1.3426399519236385,
        1.3641799511523482,
        1.3782799506474648,
        1.3833299504666379,
        1.3926199501339875,
        1.4105199494930365,
        1.4142999493576847,
        1.4449699482594738,
        1.4770299471114905,
        1.505999946074152,
        1.5133799458098938,
        1.5445099446952115,
        1.557529944229,
        1.587119943169461,
        1.63086994160289,
        1.6674799402919833,
        1.7373799377890506,
        1.8880099323953914,
        1.9530899300650502,
        2.0139799278847414,
        2.1463799231438503,
        2.153899922874579,
        2.1970599213291346,
        2.2176099205932935,
        2.2544899192727192,
        2.304199917492736,
        2.3325399164779563,
        2.3532199157374603,
        2.3842199146274337,
        2.3921999143416905,
        2.399219914090323,
        2.4383199126902566,
        2.504219910330553,
        2.515159909938821,
        2.5480599087607594,
        2.567019908081852,
        2.597909906975764,
        2.6413199054213674,
        2.642199905389857,
        2.6625599046608195,
        2.6776799041194126,
        2.7061099031014098,
        2.7068499030749127,
        2.7742599006611397,
        2.780609900433763,
        2.7908099000685285,
        2.810909899348801,
        2.816439899150786,
        2.8175398991113982,
        2.846369898079073,
        2.8500198979483766,
        2.8666498973529,
        2.8772098969747746,
        2.902419896072072,
        2.91875989548698,
        2.9441098945792636,
        2.980039893292706,
        2.9849698931161766,
        2.9952198927491516,
        3.0029398924727184,
        3.0184298919180628,
        3.0412598911005815,
        3.044569890982059,
        3.0473898908810826,
        3.0537898906519154,
        3.0724798899826764,
        3.0953398891641206,
        3.1010998889578705,
        3.1236098881518473,
        3.127969887995727,
        3.166829886604254,
        3.2090498850924685,
        3.225819884491979,
        3.2373698840784044,
        3.281189882509327,
        3.288149882260108,
        3.3250198809398914,
        3.326709880879377,
        3.351269879999949,
        3.3571998797876117,
        3.3790798790041467,
        3.389969878614205,
        3.390349878600598,
        3.418209877603006,
        3.4186598775868924,
        3.429989877181196,
        3.4577998761853936,
        3.465429875912183,
        3.4740298756042405,
        3.4972198747738683,
        3.5153098741261135,
        3.547869872960227,
        3.548779872927642,
        3.5711898721251996,
        3.59184987138542,
        3.638919869699969,
        3.6781498682952467,
        3.692059867797167,
        3.718319866856866,
        3.734879866263897,
        3.7413898660307914,
        3.7580398654345983,
        3.7811498646070913,
        3.8064498637011654,
        3.815149863389642,
        3.8176398633004816,
        3.835979862643775,
        3.855059861960571,
        3.8681798614907787,
        3.8944498605501203,
        3.9034598602274957,
        3.952019858488692,
        3.968869857885338,
        3.9757498576389843,
        3.9901098571247906,
        4.009819856419028,
        4.024659855887647,
        4.053389854858903,
        4.058699854668765,
        4.063159854509064,
        4.10973985284116,
        4.121079852435104,
        4.132129852039433,
        4.153169851286046,
        4.165829850832726,
        4.177239850424164,
        4.1972098497090915,
        4.226909848645613,
        4.23633984830795,
        4.274469846942616,
        4.3099598456718144,
        4.322459845224222,
        4.324469845152249,
        4.353479844113479,
        4.373549843394826,
        4.374329843366895,
        4.454909840481541,
        4.481919839514385,
        4.511349838460575,
        4.5569998368259705,
        4.598489835340323,
        4.658549833189735,
        4.664989832959136,
        4.688809832106205,
        4.76383982941958,
        4.791529828428075,
        4.810409827752033,
        4.830719827024787,
        4.838569826743698,
        4.8898298249082135,
        4.897199824644314,
        4.912579824093597,
        4.985719821474649,
        5.01089982057302,
        5.06191981874613,
        5.0803798180851265,
        5.106269817158075,
        5.132619816214551,
        5.13364981617767,
        5.157719815315787,
        5.1715298148212865,
        5.208739813488896,
        5.20942981346419,
        5.2267398128443645,
        5.299959810222551,
        5.305319810030624,
        5.3319498090770745,
        5.335439808952108,
        5.373299807596442,
        5.375249807526617,
        5.383619807226909,
        5.443009805100313,
        5.46977980414175,
        5.480659803752166,
        5.570949800519122,
        5.633269798287609,
        5.74092979443259,
        5.819639791614195,
        5.862679790073048,
        5.873379789689909,
        5.909879788382941,
        5.922529787929979,
        5.928639787711195,
        6.010989784762461,
        9.456179661399384,
        13.248909525591829,
        13.694089509651116,
        13.968359499830239,
        14.06765949627457
    ],
    "et": [
        -196.481403062
    ],
    "fc": [
        0.0079,
        0.0114,
        0.0247,
        0.0744,
        0.1407,
        0.209,
        0.2768,
        0.476,
        1.0224,
        0.4651,
        0.8669,
        0.8572,
        0.761,
        1.0122,
        1.1641,
        1.1985,
        1.4862,
        2.3147,
        1.4123,
        1.516,
        1.6157,
        1.4626,
        1.3351,
        1.3567,
        1.3523,
        1.3696,
        1.4083,
        1.4243,
        10.8172,
        5.5089,
        5.5434,
        5.5584,
        5.9767,
        5.9911,
        5.9896,
        6.1871,
        6.181,
        6.2345,
        6.2723
    ],
    "gap": 0.2590499907241096,
    "homo": -0.2319399916948465,
    "id": "AG7_00204",
    "ir": [
        0.4082,
        0.2138,
        1.1541,
        1.6021,
        0.262,
        0.3609,
        2.985,
        1.7665,
        1.3981,
        11.6144,
        3.1277,
        1.6102,
        2.4996,
        1.4328,
        4.2108,
        0.0272,
        11.4943,
        4.8697,
        2.8042,
        6.323,
        1.7637,
        0.7908,
        0.6819,
        1.3849,
        2.5669,
        16.1096,
        9.2935,
        4.064,
        1.5381,
        26.7735,
        81.052,
        7.7097,
        16.4091,
        17.1912,
        42.4456,
        19.2648,
        2.3748,
        21.4558,
        54.655
    ],
    "lumo": 0.02710999902926312,
    "ma": [
        12.0,
        12.0,
        12.0,
        12.0,
        12.0,
        1.00783,
        1.00783,
        1.00783,
        1.00783,
        1.00783,
        1.00783,
        1.00783,
        1.00783,
        1.00783,
        1.00783
    ],
    "mr": [
        1.0373,
        1.0337,
        1.2076,
        1.7731,
        2.6228,
        2.243,
        2.21,
        2.8312,
        2.9091,
        1.1295,
        1.5911,
        1.5368,
        1.2419,
        1.5159,
        1.719,
        1.6623,
        1.969,
        2.5728,
        1.2603,
        1.2843,
        1.3643,
        1.2192,
        1.0446,
        1.0474,
        1.044,
        1.0416,
        1.0648,
        1.0756,
        6.0832,
        1.0388,
        1.0405,
        1.0419,
        1.0991,
        1.0991,
        1.0987,
        1.098,
        1.093,
        1.0912,
        1.0925
    ],
    "mu": 0.19910143143634101,
    "mu_x": -0.0617,
    "mu_xx=": 0.7532,
    "mu_xxx=": 0.9278,
    "mu_xxy=": 0.0671,
    "mu_xxz=": 0.0,
    "mu_xy=": -0.2901,
    "mu_xyy=": 0.9557,
    "mu_xyz=": 0.0,
    "mu_xz=": 0.0,
    "mu_xzz=": -0.823,
    "mu_y": 0.1893,
    "mu_yy=": 0.4575,
    "mu_yyy=": -1.5216,
    "mu_yyz=": 0.0,
    "mu_yz=": 0.0,
    "mu_yzz=": 0.9708,
    "mu_z": 0.0,
    "mu_zz=": -1.2107,
    "mu_zzz=": 0.0,
    "na": 15,
    "ne": 40,
    "ne_down": 20,
    "ne_up": 20,
    "ni": 5,
    "oemga": [
        113.4357,
        137.0323,
        186.398,
        266.9054,
        301.7682,
        397.6577,
        461.043,
        534.203,
        772.3187,
        836.0234,
        961.6014,
        973.0147,
        1019.8578,
        1064.5848,
        1072.0904,
        1106.2194,
        1131.8484,
        1235.7393,
        1379.1179,
        1415.4337,
        1417.7688,
        1426.8829,
        1472.8564,
        1482.7048,
        1482.7286,
        1493.9091,
        1498.2278,
        1499.1922,
        1737.2631,
        3000.1257,
        3007.003,
        3009.1637,
        3037.9502,
        3041.6865,
        3041.8226,
        3092.5056,
        3098.1352,
        3114.1058,
        3121.6095
    ],
    "oemga0": 3121.6095,
    "qa": [
        -0.286117,
        -0.153774,
        0.078426,
        -0.289887,
        -0.282991,
        0.091085,
        0.097743,
        0.097743,
        0.098989,
        0.093525,
        0.093361,
        0.093362,
        0.089229,
        0.090075,
        0.089229
    ],
    "r2": 539.316,
    "rn": [
        0.0,
        0.0,
        0.0,
        0.0,
        0.0,
        0.02,
        0.0,
        0.0,
        0.01,
        0.0,
        0.0,
        -0.04,
        0.0,
        0.0,
        0.02,
        0.0,
        0.0,
        0.54,
        0.19,
        -0.43,
        -0.28,
        -0.19,
        0.43,
        -0.28,
        0.0,
        0.0,
        0.01,
        0.0,
        0.0,
        0.1,
        0.15,
        -0.02,
        -0.15,
        -0.15,
        0.02,
        -0.15,
        0.0,
        0.0,
        0.02,
        0.0,
        0.0,
        0.02,
        0.0,
        0.0,
        0.02,
        0.0,
        0.0,
        -0.04,
        0.0,
        0.0,
        0.01,
        0.0,
        0.0,
        0.02,
        0.0,
        0.0,
        0.01,
        0.0,
        0.0,
        0.01,
        0.0,
        0.0,
        -0.23,
        -0.02,
        0.15,
        0.03,
        0.02,
        -0.15,
        0.03,
        0.0,
        0.0,
        0.02,
        0.0,
        0.0,
        0.53,
        0.45,
        0.05,
        -0.27,
        -0.45,
        -0.05,
        -0.27,
        -0.05,
        0.1,
        0.07,
        0.0,
        0.0,
        -0.13,
        0.05,
        -0.1,
        0.07,
        0.0,
        0.0,
        0.07,
        0.0,
        0.0,
        -0.06,
        0.0,
        0.0,
        -0.06,
        0.0,
        0.0,
        -0.05,
        0.0,
        0.0,
        0.06,
        0.0,
        0.0,
        0.13,
        -0.09,
        -0.04,
        0.12,
        0.09,
        0.04,
        0.12,
        0.0,
        0.0,
        -0.09,
        0.0,
        0.0,
        -0.12,
        -0.06,
        -0.01,
        -0.01,
        0.06,
        0.01,
        -0.01,
        -0.31,
        0.34,
        0.37,
        0.0,
        0.0,
        -0.42,
        0.31,
        -0.34,
        0.37,
        0.0,
        0.0,
        -0.09,
        0.0,
        0.0,
        0.21,
        0.0,
        0.0,
        0.08,
        0.0,
        0.0,
        -0.01,
        0.0,
        0.0,
        -0.11,
        0.0,
        0.0,
        -0.18,
        0.23,
        0.06,
        -0.22,
        -0.23,
        -0.06,
        -0.22,
        0.0,
        0.0,
        0.31,
        0.0,
        0.0,
        -0.2,
        -0.15,
        -0.06,
        0.07,
        0.15,
        0.06,
        0.07,
        -0.02,
        0.33,
        0.0,
        0.0,
        0.0,
        -0.53,
        0.02,
        -0.33,
        0.0,
        -0.11,
        0.2,
        0.0,
        0.01,
        -0.1,
        0.0,
        0.0,
        -0.13,
        0.0,
        0.2,
        -0.11,
        0.0,
        -0.11,
        0.06,
        0.0,
        -0.38,
        0.2,
        0.0,
        -0.02,
        0.36,
        0.0,
        -0.02,
        0.36,
        0.0,
        0.15,
        -0.11,
        0.0,
        0.25,
        -0.21,
        0.0,
        0.24,
        -0.03,
        0.0,
        0.24,
        -0.03,
        0.0,
        -0.06,
        0.17,
        0.0,
        -0.29,
        0.03,
        0.0,
        -0.06,
        0.17,
        0.0,
        -0.11,
        0.01,
        0.0,
        -0.1,
        0.05,
        0.0,
        -0.08,
        0.06,
        0.0,
        0.17,
        0.11,
        0.0,
        0.06,
        -0.18,
        0.0,
        -0.06,
        0.0,
        0.0,
        -0.12,
        -0.02,
        0.0,
        -0.12,
        -0.02,
        0.0,
        -0.11,
        0.05,
        0.0,
        0.31,
        -0.14,
        0.0,
        0.26,
        0.26,
        0.0,
        0.26,
        0.26,
        0.0,
        -0.01,
        -0.38,
        -0.01,
        0.38,
        -0.13,
        0.0,
        -0.01,
        -0.38,
        0.01,
        0.0,
        0.0,
        0.0,
        0.0,
        0.0,
        -0.13,
        0.0,
        0.0,
        0.3,
        0.0,
        0.0,
        -0.04,
        0.0,
        0.0,
        -0.02,
        0.0,
        0.0,
        0.04,
        -0.13,
        -0.01,
        0.08,
        0.13,
        0.01,
        0.08,
        0.0,
        0.0,
        -0.43,
        0.0,
        0.0,
        -0.29,
        0.02,
        -0.37,
        -0.19,
        -0.02,
        0.37,
        -0.19,
        0.22,
        0.17,
        -0.13,
        0.0,
        0.0,
        -0.19,
        -0.22,
        -0.17,
        -0.13,
        0.21,
        0.04,
        0.0,
        0.04,
        0.19,
        0.0,
        -0.13,
        -0.06,
        0.0,
        0.04,
        -0.06,
        0.0,
        -0.22,
        -0.08,
        0.0,
        0.57,
        0.04,
        0.0,
        0.1,
        -0.16,
        -0.01,
        0.1,
        -0.16,
        0.01,
        0.17,
        0.18,
        0.0,
        0.19,
        -0.31,
        0.0,
        0.14,
        0.1,
        -0.01,
        0.14,
        0.1,
        0.01,
        -0.21,
        -0.04,
        0.0,
        -0.29,
        -0.09,
        0.0,
        -0.21,
        -0.04,
        0.0,
        -0.13,
        0.01,
        0.0,
        -0.06,
        0.2,
        0.0,
        -0.04,
        0.02,
        0.0,
        0.03,
        -0.26,
        0.0,
        0.17,
        0.11,
        0.0,
        0.33,
        0.01,
        0.0,
        -0.26,
        -0.27,
        -0.02,
        -0.26,
        -0.27,
        0.02,
        -0.01,
        0.2,
        0.0,
        0.08,
        -0.37,
        0.0,
        0.05,
        -0.23,
        0.0,
        0.05,
        -0.23,
        0.0,
        0.18,
        0.15,
        0.0,
        0.15,
        0.11,
        0.0,
        0.18,
        0.15,
        0.0,
        0.0,
        0.0,
        0.04,
        0.0,
        0.0,
        0.08,
        0.0,
        0.0,
        -0.03,
        0.0,
        0.0,
        0.02,
        0.0,
        0.0,
        -0.03,
        0.0,
        0.0,
        -0.13,
        0.24,
        0.11,
        -0.08,
        -0.24,
        -0.11,
        -0.08,
        0.0,
        0.0,
        -0.8,
        0.0,
        0.0,
        -0.08,
        0.03,
        -0.14,
        -0.05,
        -0.03,
        0.14,
        -0.05,
        -0.19,
        -0.1,
        0.07,
        0.0,
        0.0,
        0.14,
        0.19,
        0.1,
        0.07,
        0.11,
        -0.01,
        0.0,
        -0.06,
        -0.02,
        0.0,
        -0.03,
        0.1,
        0.0,
        0.05,
        -0.11,
        0.0,
        -0.06,
        0.09,
        0.0,
        -0.18,
        -0.01,
        0.0,
        0.19,
        0.2,
        0.02,
        0.19,
        0.2,
        -0.02,
        -0.26,
        -0.02,
        0.0,
        -0.04,
        0.04,
        0.0,
        -0.05,
        -0.24,
        0.02,
        -0.05,
        -0.24,
        -0.02,
        -0.15,
        -0.31,
        -0.04,
        0.54,
        0.18,
        0.0,
        -0.15,
        -0.31,
        0.04,
        -0.1,
        0.02,
        0.0,
        0.06,
        0.04,
        0.0,
        0.09,
        0.01,
        0.0,
        0.11,
        0.02,
        0.0,
        -0.11,
        -0.03,
        0.0,
        0.19,
        0.01,
        0.0,
        -0.19,
        -0.21,
        -0.03,
        -0.19,
        -0.21,
        0.03,
        0.21,
        0.04,
        0.0,
        -0.21,
        0.57,
        0.0,
        -0.16,
        -0.32,
        0.05,
        -0.16,
        -0.32,
        -0.05,
        -0.13,
        -0.15,
        -0.02,
        0.03,
        -0.01,
        0.0,
        -0.13,
        -0.15,
        0.02,
        0.0,
        0.0,
        -0.02,
        0.0,
        0.0,
        -0.03,
        0.0,
        0.0,
        0.0,
        0.0,
        0.0,
        0.11,
        0.0,
        0.0,
        -0.09,
        0.0,
        0.0,
        0.03,
        -0.08,
        -0.03,
        0.02,
        0.08,
        0.03,
        0.02,
        0.0,
        0.0,
        0.42,
        0.0,
        0.0,
        -0.22,
        0.1,
        -0.42,
        -0.12,
        -0.1,
        0.42,
        -0.12,
        -0.34,
        -0.17,
        0.11,
        0.0,
        0.0,
        0.17,
        0.34,
        0.17,
        0.11,
        0.0,
        0.0,
        0.15,
        0.0,
        0.0,
        -0.15,
        0.0,
        0.0,
        0.02,
        0.0,
        0.0,
        0.0,
        0.0,
        0.0,
        0.01,
        0.0,
        0.0,
        -0.32,
        0.56,
        0.13,
        -0.18,
        -0.56,
        -0.13,
        -0.18,
        0.0,
        0.0,
        0.34,
        0.0,
        0.0,
        0.0,
        0.0,
        0.0,
        0.0,
        0.0,
        0.0,
        0.0,
        0.03,
        0.01,
        -0.01,
        0.0,
        0.0,
        -0.02,
        -0.03,
        -0.01,
        -0.01,
        0.02,
        0.12,
        0.0,
        -0.04,
        -0.15,
        0.0,
        -0.05,
        -0.08,
        0.0,
        -0.04,
        0.05,
        0.0,
        0.02,
        0.11,
        0.0,
        0.57,
        0.12,
        0.0,
        -0.09,
        -0.24,
        -0.06,
        -0.09,
        -0.24,
        0.06,
        0.35,
        -0.17,
        0.0,
        0.02,
        -0.06,
        0.0,
        0.01,
        0.12,
        -0.01,
        0.01,
        0.12,
        0.01,
        -0.02,
        -0.17,
        -0.04,
        0.44,
        0.17,
        0.0,
        -0.02,
        -0.17,
        0.04,
        0.0,
        0.0,
        -0.01,
        0.0,
        0.0,
        -0.02,
        0.0,
        0.0,
        0.18,
        0.0,
        0.0,
        -0.11,
        0.0,
        0.0,
        -0.12,
        0.0,
        0.0,
        0.01,
        -0.03,
        -0.01,
        0.01,
        0.03,
        0.01,
        0.01,
        0.0,
        0.0,
        0.03,
        0.0,
        0.0,
        0.26,
        -0.13,
        0.38,
        0.12,
        0.13,
        -0.38,
        0.12,
        -0.42,
        -0.16,
        0.14,
        0.0,
        0.0,
        0.27,
        0.42,
        0.16,
        0.14,
        -0.1,
        -0.09,
        0.0,
        0.19,
        0.06,
        0.0,
        0.08,
        -0.01,
        0.0,
        -0.1,
        -0.02,
        0.0,
        -0.09,
        0.08,
        0.0,
        -0.34,
        -0.09,
        0.0,
        -0.08,
        0.0,
        0.02,
        -0.08,
        0.0,
        -0.02,
        0.35,
        0.06,
        0.0,
        0.12,
        -0.39,
        0.0,
        0.14,
        0.25,
        -0.06,
        0.14,
        0.25,
        0.06,
        -0.14,
        -0.25,
        -0.05,
        0.35,
        0.14,
        0.0,
        -0.14,
        -0.25,
        0.05,
        -0.03,
        0.1,
        0.0,
        0.0,
        -0.12,
        0.0,
        0.2,
        0.24,
        0.0,
        -0.08,
        -0.07,
        0.0,
        -0.06,
        -0.07,
        0.0,
        0.39,
        0.1,
        0.0,
        -0.07,
        -0.16,
        -0.07,
        -0.07,
        -0.16,
        0.07,
        -0.45,
        -0.1,
        0.0,
        0.14,
        -0.44,
        0.0,
        0.12,
        0.04,
        -0.08,
        0.12,
        0.04,
        0.08,
        -0.12,
        -0.07,
        0.04,
        -0.31,
        -0.11,
        0.0,
        -0.12,
        -0.07,
        -0.04,
        -0.03,
        -0.05,
        0.0,
        -0.04,
        -0.03,
        0.0,
        -0.03,
        0.12,
        0.0,
        0.0,
        0.03,
        0.0,
        0.02,
        -0.03,
        0.0,
        0.14,
        -0.04,
        0.0,
        0.17,
        0.18,
        -0.03,
        0.17,
        0.18,
        0.03,
        0.77,
        -0.05,
        0.0,
        0.13,
        -0.23,
        0.0,
        -0.03,
        -0.25,
        -0.07,
        -0.03,
        -0.25,
        0.07,
        -0.07,
        0.08,
        0.08,
        -0.09,
        -0.04,
        0.0,
        -0.07,
        0.08,
        -0.08,
        0.05,
        0.01,
        0.0,
        0.0,
        0.01,
        0.0,
        -0.02,
        -0.05,
        0.0,
        -0.01,
        0.07,
        0.0,
        0.1,
        0.06,
        0.0,
        -0.19,
        0.01,
        0.0,
        -0.19,
        -0.07,
        0.11,
        -0.19,
        -0.07,
        -0.11,
        -0.1,
        0.01,
        0.0,
        0.12,
        -0.17,
        0.0,
        0.05,
        -0.27,
        -0.15,
        0.05,
        -0.27,
        0.15,
        -0.33,
        -0.28,
        0.18,
        -0.39,
        -0.03,
        0.0,
        -0.33,
        -0.28,
        -0.18,
        0.12,
        0.03,
        0.0,
        -0.04,
        -0.04,
        0.0,
        -0.01,
        0.09,
        0.0,
        0.01,
        -0.07,
        0.0,
        0.0,
        -0.03,
        0.0,
        -0.45,
        0.02,
        0.0,
        -0.39,
        -0.18,
        0.23,
        -0.39,
        -0.18,
        -0.23,
        0.4,
        -0.05,
        0.0,
        -0.1,
        0.12,
        0.0,
        0.0,
        0.18,
        0.09,
        0.0,
        0.18,
        -0.09,
        -0.01,
        0.11,
        0.04,
        0.02,
        -0.02,
        0.0,
        -0.01,
        0.11,
        -0.04,
        0.04,
        0.02,
        0.0,
        0.0,
        0.0,
        0.0,
        0.02,
        -0.02,
        0.0,
        -0.03,
        0.09,
        0.0,
        -0.08,
        -0.03,
        0.0,
        -0.12,
        0.01,
        0.0,
        -0.18,
        -0.05,
        0.11,
        -0.18,
        -0.05,
        -0.11,
        -0.11,
        0.0,
        0.0,
        0.17,
        -0.25,
        0.0,
        0.1,
        -0.37,
        -0.23,
        0.1,
        -0.37,
        0.23,
        0.28,
        0.17,
        -0.17,
        0.31,
        0.03,
        0.0,
        0.28,
        0.17,
        0.17,
        0.0,
        0.0,
        0.01,
        0.0,
        0.0,
        0.0,
        0.0,
        0.0,
        0.0,
        0.0,
        0.0,
        -0.04,
        0.0,
        0.0,
        0.04,
        0.0,
        0.0,
        -0.12,
        -0.03,
        -0.08,
        -0.01,
        0.03,
        0.08,
        -0.01,
        0.0,
        0.0,
        -0.01,
        0.0,
        0.0,
        0.44,
        -0.21,
        -0.22,
        0.04,
        0.21,
        0.22,
        0.04,
        -0.06,
        -0.37,
        -0.04,
        0.0,
        0.0,
        -0.55,
        0.06,
        0.37,
        -0.04,
        -0.01,
        0.03,
        0.0,
        0.0,
        0.0,
        0.0,
        -0.02,
        0.0,
        0.0,
        -0.03,
        -0.02,
        0.0,
        0.01,
        -0.03,
        0.0,
        -0.22,
        0.02,
        0.0,
        0.2,
        -0.23,
        -0.22,
        0.2,
        -0.22,
        0.22,
        0.0,
        0.0,
        0.0,
        -0.15,
        0.22,
        0.0,
        0.31,
        -0.04,
        -0.22,
        0.31,
        -0.04,
        0.22,
        -0.2,
        0.21,
        0.2,
        0.23,
        0.02,
        0.0,
        -0.2,
        0.21,
        -0.2,
        0.0,
        0.0,
        -0.05,
        0.0,
        0.0,
        -0.02,
        0.0,
        0.0,
        0.01,
        0.0,
        0.0,
        0.0,
        0.0,
        0.0,
        0.01,
        0.0,
        0.0,
        0.69,
        0.15,
        0.46,
        0.05,
        -0.15,
        -0.46,
        0.05,
        0.0,
        0.0,
        0.03,
        0.0,
        0.0,
        0.0,
        0.01,
        0.01,
        0.0,
        0.0,
        -0.01,
        0.0,
        -0.02,
        -0.11,
        -0.01,
        0.0,
        0.0,
        -0.16,
        0.01,
        0.11,
        -0.01,
        0.0,
        0.0,
        -0.01,
        0.0,
        0.0,
        0.0,
        0.0,
        0.0,
        -0.03,
        0.0,
        0.0,
        -0.04,
        0.0,
        0.0,
        -0.03,
        0.0,
        0.0,
        0.11,
        0.02,
        0.07,
        0.01,
        -0.02,
        -0.07,
        0.01,
        0.0,
        0.0,
        0.02,
        0.0,
        0.0,
        0.55,
        -0.25,
        -0.3,
        0.04,
        0.25,
        0.3,
        0.04,
        0.06,
        0.29,
        0.03,
        0.0,
        0.0,
        0.42,
        -0.06,
        -0.29,
        0.03,
        0.0,
        -0.05,
        0.0,
        -0.02,
        0.0,
        0.0,
        0.03,
        -0.02,
        0.0,
        -0.03,
        -0.02,
        0.0,
        0.0,
        -0.01,
        0.0,
        0.41,
        -0.02,
        0.0,
        -0.21,
        0.35,
        0.27,
        -0.21,
        0.35,
        -0.27,
        -0.04,
        0.0,
        0.0,
        -0.16,
        0.24,
        0.0,
        0.26,
        0.05,
        -0.16,
        0.26,
        0.05,
        0.16,
        -0.11,
        0.08,
        0.1,
        0.12,
        0.01,
        0.0,
        -0.11,
        0.08,
        -0.1,
        -0.01,
        0.0,
        0.0,
        0.05,
        -0.01,
        0.0,
        0.0,
        -0.02,
        0.0,
        0.03,
        0.03,
        0.0,
        0.01,
        -0.04,
        0.0,
        0.06,
        0.0,
        0.0,
        -0.08,
        0.03,
        0.05,
        -0.08,
        0.03,
        -0.05,
        -0.18,
        -0.01,
        0.0,
        0.17,
        -0.24,
        0.0,
        -0.3,
        -0.01,
        0.19,
        -0.3,
        -0.01,
        -0.19,
        -0.27,
        0.29,
        0.27,
        0.37,
        0.04,
        0.0,
        -0.27,
        0.29,
        -0.27,
        -0.06,
        0.01,
        0.0,
        0.44,
        -0.16,
        0.0,
        -0.43,
        0.22,
        0.0,
        0.04,
        -0.04,
        0.0,
        0.04,
        -0.01,
        0.0,
        0.21,
        0.01,
        0.0,
        -0.17,
        0.0,
        0.08,
        -0.17,
        0.0,
        -0.08,
        -0.37,
        -0.19,
        0.0,
        -0.11,
        0.21,
        0.0,
        0.1,
        -0.15,
        -0.1,
        0.1,
        -0.15,
        0.1,
        0.17,
        0.02,
        -0.09,
        -0.18,
        -0.03,
        0.0,
        0.17,
        0.02,
        0.09,
        0.0,
        0.0,
        0.0,
        0.0,
        0.0,
        0.0,
        0.0,
        0.0,
        0.0,
        0.01,
        -0.01,
        0.0,
        -0.05,
        0.0,
        0.0,
        0.0,
        -0.01,
        0.0,
        -0.01,
        0.0,
        -0.01,
        -0.01,
        0.0,
        0.01,
        0.0,
        -0.01,
        0.0,
        0.09,
        0.04,
        0.0,
        -0.12,
        0.06,
        -0.19,
        -0.12,
        0.06,
        0.19,
        0.33,
        -0.14,
        0.5,
        -0.07,
        0.33,
        0.0,
        0.33,
        -0.14,
        -0.5,
        -0.03,
        0.0,
        0.0,
        0.0,
        0.0,
        0.0,
        0.0,
        0.0,
        0.0,
        -0.02,
        0.03,
        0.0,
        -0.01,
        0.0,
        0.0,
        -0.01,
        0.22,
        0.0,
        0.21,
        -0.13,
        0.35,
        0.21,
        -0.13,
        -0.35,
        0.0,
        0.0,
        0.0,
        -0.19,
        -0.1,
        0.0,
        0.25,
        -0.13,
        0.39,
        0.25,
        -0.13,
        -0.39,
        0.1,
        -0.04,
        0.15,
        -0.02,
        0.1,
        0.0,
        0.1,
        -0.04,
        -0.15,
        -0.04,
        0.01,
        0.0,
        0.0,
        0.0,
        0.0,
        0.0,
        0.0,
        0.0,
        0.02,
        -0.03,
        0.0,
        0.01,
        0.0,
        0.0,
        -0.01,
        0.22,
        0.0,
        0.25,
        -0.16,
        0.42,
        0.25,
        -0.16,
        -0.42,
        0.0,
        0.05,
        0.0,
        0.15,
        0.07,
        0.0,
        -0.21,
        0.11,
        -0.34,
        -0.21,
        0.11,
        0.34,
        -0.07,
        0.03,
        -0.11,
        0.02,
        -0.08,
        0.0,
        -0.07,
        0.03,
        0.11,
        0.0,
        0.0,
        0.01,
        0.0,
        0.0,
        0.0,
        0.0,
        0.0,
        0.0,
        0.0,
        0.0,
        -0.03,
        0.0,
        0.0,
        0.09,
        0.0,
        0.0,
        0.0,
        -0.04,
        0.02,
        -0.06,
        0.04,
        -0.02,
        -0.06,
        0.0,
        0.0,
        0.0,
        0.0,
        0.0,
        -0.01,
        0.11,
        -0.06,
        0.16,
        -0.11,
        0.06,
        0.16,
        -0.38,
        0.16,
        -0.53,
        0.0,
        0.0,
        0.02,
        0.38,
        -0.16,
        -0.53,
        0.0,
        0.0,
        -0.09,
        0.0,
        0.0,
        0.0,
        0.0,
        0.0,
        0.0,
        0.0,
        0.0,
        0.0,
        0.0,
        0.0,
        0.01,
        0.0,
        0.0,
        -0.02,
        0.36,
        -0.22,
        0.55,
        -0.36,
        0.22,
        0.55,
        0.0,
        0.0,
        0.0,
        0.0,
        0.0,
        0.0,
        -0.01,
        0.01,
        -0.02,
        0.01,
        -0.01,
        -0.02,
        -0.05,
        0.02,
        -0.06,
        0.0,
        0.0,
        0.0,
        0.05,
        -0.02,
        -0.06,
        0.0,
        0.0,
        0.01,
        0.0,
        0.0,
        0.0,
        0.0,
        0.0,
        0.0,
        0.0,
        0.0,
        0.09,
        0.0,
        0.0,
        0.03,
        0.0,
        0.0,
        0.0,
        -0.02,
        0.01,
        -0.04,
        0.02,
        -0.01,
        -0.04,
        0.0,
        0.0,
        0.0,
        0.0,
        0.0,
        0.02,
        -0.36,
        0.19,
        -0.53,
        0.36,
        -0.19,
        -0.53,
        -0.11,
        0.05,
        -0.16,
        0.0,
        0.0,
        0.0,
        0.11,
        -0.05,
        -0.16,
        0.0,
        0.01,
        0.0,
        0.0,
        -0.02,
        0.0,
        0.0,
        0.0,
        0.0,
        0.0,
        0.0,
        0.0,
        -0.03,
        0.08,
        0.0,
        0.0,
        -0.13,
        0.0,
        0.01,
        0.0,
        0.02,
        0.01,
        0.0,
        -0.02,
        0.01,
        0.26,
        0.0,
        0.02,
        0.01,
        0.0,
        0.01,
        -0.01,
        0.01,
        0.01,
        -0.01,
        -0.01,
        0.13,
        -0.04,
        0.2,
        0.15,
        -0.87,
        0.0,
        0.13,
        -0.04,
        -0.2,
        0.01,
        -0.07,
        0.0,
        0.0,
        0.04,
        0.0,
        0.0,
        0.0,
        0.0,
        0.02,
        0.01,
        0.0,
        -0.01,
        0.02,
        0.0,
        -0.01,
        0.75,
        0.0,
        -0.07,
        0.03,
        -0.13,
        -0.07,
        0.03,
        0.13,
        -0.01,
        -0.5,
        0.0,
        -0.21,
        -0.12,
        0.0,
        -0.03,
        0.02,
        -0.06,
        -0.03,
        0.02,
        0.06,
        0.03,
        -0.01,
        0.04,
        0.04,
        -0.24,
        0.0,
        0.03,
        -0.01,
        -0.04,
        0.01,
        -0.02,
        0.0,
        0.0,
        -0.06,
        0.0,
        0.0,
        0.0,
        0.0,
        0.05,
        0.02,
        0.0,
        0.0,
        -0.01,
        0.0,
        0.0,
        0.24,
        0.0,
        -0.04,
        0.02,
        -0.07,
        -0.04,
        0.02,
        0.07,
        0.02,
        0.69,
        0.0,
        -0.55,
        -0.31,
        0.0,
        -0.05,
        0.04,
        -0.1,
        -0.05,
        0.04,
        0.1,
        -0.01,
        0.0,
        -0.02,
        -0.02,
        0.13,
        0.0,
        -0.01,
        0.0,
        0.02,
        0.01,
        -0.05,
        0.0,
        0.0,
        -0.04,
        0.0,
        0.0,
        0.0,
        0.0,
        -0.06,
        -0.02,
        0.0,
        0.0,
        -0.01,
        0.0,
        -0.01,
        0.51,
        0.0,
        -0.06,
        0.03,
        -0.1,
        -0.06,
        0.03,
        0.1,
        0.01,
        0.45,
        0.0,
        0.59,
        0.33,
        0.0,
        0.06,
        -0.04,
        0.11,
        0.06,
        -0.04,
        -0.11,
        -0.01,
        0.0,
        -0.01,
        -0.01,
        0.07,
        0.0,
        -0.01,
        0.0,
        0.01
    ],
    "smi": "CC=C(C)C",
    "symbols": [
        "C",
        "C",
        "C",
        "C",
        "C",
        "H",
        "H",
        "H",
        "H",
        "H",
        "H",
        "H",
        "H",
        "H",
        "H"
    ],
    "zpe": 0.135419,
    "zs": [
        6,
        6,
        6,
        6,
        6,
        1,
        1,
        1,
        1,
        1,
        1,
        1,
        1,
        1,
        1
    ]
}