{
    "A": 10.07944,
    "B": 3.41845,
    "C": 2.95083,
    "Cv": "21.965",
    "G": -196.357029,
    "H": -196.321419,
    "P": 1.0,
    "S": 0.0001194365252390397,
    "T": 298.15,
    "U": -196.322364,
    "U0": -196.328401,
    "alpha": 40.178333333333335,
    "alpha_xx": 67.251,
    "alpha_xy": 0.0,
    "alpha_xz": 57.695,
    "alpha_yy": 0.509,
    "alpha_yz": 0.0,
    "alpha_zz": 52.775,
    "bo": [
        0,
        1,
        0,
        0,
        0,
        1,
        1,
        1,
        0,
        0,
        0,
        0,
        0,
        0,
        0,
        1,
        0,
        1,
        1,
        0,
        0,
        0,
        0,
        1,
        0,
        0,
        0,
        0,
        0,
        0,
        0,
        1,
        0,
        1,
        0,
        0,
        0,
        0,
        0,
        1,
        1,
        0,
        0,
        0,
        0,
        0,
        1,
        1,
        0,
        1,
        0,
        0,
        0,
        0,
        0,
        0,
        1,
        0,
        0,
        0,
        0,
        0,
        0,
        1,
        0,
        0,
        0,
        0,
        0,
        0,
        0,
        0,
        1,
        1,
        1,
        1,
        0,
        0,
        0,
        0,
        0,
        0,
        0,
        0,
        0,
        0,
        0,
        0,
        0,
        0,
        1,
        0,
        0,
        0,
        0,
        0,
        0,
        0,
        0,
        0,
        0,
        0,
        0,
        0,
        0,
        1,
        0,
        0,
        0,
        0,
        0,
        0,
        0,
        0,
        0,
        0,
        0,
        0,
        0,
        0,
        0,
        1,
        0,
        0,
        0,
        0,
        0,
        0,
        0,
        0,
        0,
        0,
        0,
        0,
        0,
        0,
        0,
        1,
        0,
        0,
        0,
        0,
        0,
        0,
        0,
        0,
        0,
        0,
        0,
        0,
        0,
        0,
        1,
        0,
        0,
        0,
        0,
        0,
        0,
        0,
        0,
        0,
        0,
        0,
        0,
        0,
        0,
        0,
        1,
        0,
        0,
        0,
        0,
        0,
        0,
        0,
        0,
        0,
        0,
        0,
        0,
        0,
        0,
        0,
        1,
        0,
        0,
        0,
        0,
        0,
        0,
        0,
        0,
        0,
        0,
        0,
        0,
        0,
        0,
        1,
        0,
        0,
        0,
        0,
        0,
        0,
        0,
        0,
        0,
        0,
        0,
        0,
        0,
        0,
        1,
        0,
        0,
        0,
        0,
        0,
        0,
        0,
        0,
        0,
        0
    ],
    "coords": [
        -1.955706,
        -0.500464,
        0.074207,
        -0.606667,
        -0.064285,
        -0.444724,
        0.0,
        1.243033,
        0.0,
        0.606667,
        -0.064285,
        0.444724,
        1.955706,
        -0.500464,
        -0.074207,
        -2.08855,
        -0.203895,
        1.116802,
        -2.071503,
        -1.585756,
        0.021806,
        -2.768236,
        -0.050987,
        -0.501715,
        -0.416653,
        -0.332726,
        -1.478631,
        -0.545557,
        1.83098,
        0.726877,
        0.545557,
        1.83098,
        -0.726877,
        0.416653,
        -0.332726,
        1.478631,
        2.768236,
        -0.050986,
        0.501714,
        2.071503,
        -1.585756,
        -0.021804,
        2.088549,
        -0.203897,
        -1.116802
    ],
    "e ne": -815.1863311194,
    "e_disp": -0.007995218799976556,
    "e_k": 195.1315478569,
    "e_nn": 180.4770734124,
    "eigs": [
        -10.172109635763839,
        -10.171829635773864,
        -10.16209963612227,
        -10.159069636230766,
        -10.159069636230766,
        -0.8588099692483018,
        -0.724239974066895,
        -0.6877499753735046,
        -0.5757299793846424,
        -0.5595199799650794,
        -0.47006998316804555,
        -0.4580899835970174,
        -0.41113998527817186,
        -0.4010499856394679,
        -0.3847699862224113,
        -0.3840399862485507,
        -0.3497299874771004,
        -0.3445199876636566,
        -0.2764299901017781,
        -0.268399990389311,
        0.04576999836109823,
        0.058709997897751304,
        0.06519999766536169,
        0.08211999705950156,
        0.10834999612027515,
        0.10869999610774257,
        0.11789999577831509,
        0.1257199954983017,
        0.12665999546464282,
        0.1352799951559836,
        0.1479799947012304,
        0.17017999390630756,
        0.18710999330008934,
        0.24700999115522992,
        0.25168999098765166,
        0.25200999097619325,
        0.2615099906360236,
        0.2733899902106324,
        0.2903799896022658,
        0.2919699895453321,
        0.2965999893795441,
        0.34862998751648844,
        0.3983299857368639,
        0.40670998543679837,
        0.4270299847091933,
        0.43125998455772824,
        0.45288998378321565,
        0.45425998373415954,
        0.4595199835458129,
        0.46032998351680904,
        0.46432998337357967,
        0.4684599832256954,
        0.4700799831676875,
        0.47526998298184747,
        0.48918998248340934,
        0.504899981920876,
        0.5050699819147888,
        0.5150299815581477,
        0.5176999814625423,
        0.5294099810432382,
        0.5498699803106201,
        0.6305199774227584,
        0.7045599747715833,
        0.7131499744639982,
        0.716869974330795,
        0.7486899731914055,
        0.7875799717988582,
        0.7884899717662737,
        0.8137599708614224,
        0.852909969459565,
        0.8678399689249615,
        0.8731299687355406,
        0.9009499677393806,
        0.9292899667246006,
        0.948729966028506,
        0.9592799656507388,
        0.9688799653069882,
        0.9993899642145064,
        1.0121899637561724,
        1.030399963104121,
        1.0390499627943874,
        1.0469199625125838,
        1.0505199623836772,
        1.0660299618283056,
        1.091839960904118,
        1.1057599604056803,
        1.1185199599487785,
        1.133339959418114,
        1.1368299592931461,
        1.1764599578741015,
        1.178449957802845,
        1.1938899572499795,
        1.1940399572446085,
        1.2413299555512798,
        1.2470999553446713,
        1.2822399540864016,
        1.287909953883374,
        1.3119199530236396,
        1.317469952824909,
        1.3308599523454487,
        1.347329951755702,
        1.3635799511738327,
        1.3734899508189822,
        1.3757199507391318,
        1.3994399498897816,
        1.4187799491972677,
        1.4194599491729187,
        1.4371499485394872,
        1.4657799475143232,
        1.4757099471587563,
        1.4875399467351555,
        1.515519945733266,
        1.5193899455946918,
        1.558869944181018,
        1.5981999427727158,
        1.6444399411169843,
        1.6557399407123614,
        1.6899499394873925,
        1.7592299370066604,
        1.8135499350616058,
        2.1433299232530625,
        2.1655399224577816,
        2.206619920986816,
        2.245259919603221,
        2.2623499189912737,
        2.3089799173215773,
        2.3328499164668566,
        2.3362399163454692,
        2.361839915428801,
        2.386299914552954,
        2.415789913496996,
        2.435529912790159,
        2.499889910485599,
        2.5256699095624855,
        2.5346899092395034,
        2.5564299084610522,
        2.592469907170556,
        2.627139905929115,
        2.6523299050271287,
        2.6665099045193807,
        2.698609903369965,
        2.72733990234122,
        2.7294399022660247,
        2.7356399020440194,
        2.7611299011312904,
        2.764289901018139,
        2.776729900572696,
        2.7949798999192117,
        2.810389899367421,
        2.826879898776958,
        2.85683989770417,
        2.8691498972633815,
        2.8812798968290387,
        2.9091398958314465,
        2.92638989521377,
        2.9529198942638013,
        2.956499894135611,
        2.975619893450975,
        2.9821798932160783,
        3.008059892289385,
        3.0188698919023076,
        3.030259891494462,
        3.0429498910400667,
        3.0438198910089147,
        3.08718988945595,
        3.104949888820012,
        3.1205798882603433,
        3.1322698878417556,
        3.1391298875961176,
        3.1567098869666244,
        3.1640698867030825,
        3.1953898855815965,
        3.2269098844529496,
        3.2387798840279163,
        3.284979882373617,
        3.302669881740185,
        3.3123398813939287,
        3.350139880040411,
        3.3584398797432105,
        3.3625698795953256,
        3.3746498791627735,
        3.3986398783037557,
        3.4052798780659947,
        3.463659875975562,
        3.4684398758044037,
        3.47132987570092,
        3.4805898753693443,
        3.5212298739141343,
        3.5418698731750706,
        3.550569872863547,
        3.559059872559543,
        3.6041998709431997,
        3.6149598705579127,
        3.6229098702732445,
        3.6659998687303057,
        3.6741598684381183,
        3.7217298667347634,
        3.7312298663945938,
        3.7410498660429656,
        3.76603986514814,
        3.771679864946187,
        3.7797998646554314,
        3.8104798635568624,
        3.8204898631984308,
        3.842929862394914,
        3.8746898612576732,
        3.890069860706957,
        3.8964298604792216,
        3.896589860473493,
        3.911379859943902,
        3.9248598594612187,
        3.9254298594408086,
        4.011689856352068,
        4.012989856305519,
        4.02757985578309,
        4.0526498548853995,
        4.056509854747183,
        4.059179854651577,
        4.091499853494285,
        4.110789852803561,
        4.118379852531784,
        4.121479852420781,
        4.130209852108182,
        4.168349850742491,
        4.175409850489691,
        4.1888298500091565,
        4.202839849507496,
        4.221749848830379,
        4.25133984777084,
        4.26623984723731,
        4.266579847225136,
        4.322619845218493,
        4.324389845155115,
        4.364369843723537,
        4.379949843165659,
        4.386529842930046,
        4.423599841602669,
        4.438929841053742,
        4.462349840215134,
        4.4654798401030575,
        4.529159837822847,
        4.585979835788273,
        4.594439835485343,
        4.646759833611903,
        4.750949829881136,
        4.78033982882876,
        4.813219827651414,
        4.846199826470488,
        4.856699826094511,
        4.9123598241014745,
        4.923849823690048,
        4.934509823308343,
        4.9546698225864665,
        4.983189821565241,
        4.993949821179954,
        5.017139820349582,
        5.043939819389946,
        5.088889817780406,
        5.1272998164050465,
        5.160909815201562,
        5.18555981431891,
        5.209529813460608,
        5.242259812288634,
        5.259269811679552,
        5.272789811195436,
        5.347499808520271,
        5.352359808346247,
        5.369229807742178,
        5.383549807229416,
        5.387119807101585,
        5.396939806749956,
        5.41890980596327,
        5.468649804182212,
        5.47361980400425,
        5.516449802470621,
        5.529439802005484,
        5.593819799700208,
        5.684329796459285,
        5.7833197929147175,
        5.8220497915279,
        5.9010597886987615,
        5.9018097886719065,
        5.9290697876957985,
        5.933209787547555,
        5.997529785244429,
        10.987499606566896,
        12.142109565223388,
        12.851829539810206,
        13.554279514657342,
        13.571359514045753
    ],
    "et": [
        -196.465439107
    ],
    "fc": [
        0.0248,
        0.0295,
        0.0671,
        0.1108,
        0.2539,
        0.2264,
        0.9922,
        0.8036,
        0.5135,
        0.6917,
        0.8529,
        0.72,
        0.8337,
        1.705,
        0.8409,
        1.0949,
        1.2987,
        1.4835,
        1.4596,
        1.626,
        1.3918,
        1.4191,
        1.4915,
        1.9341,
        1.3682,
        1.385,
        1.4501,
        1.382,
        1.8583,
        5.5272,
        5.5324,
        6.0949,
        6.0952,
        6.11,
        6.1192,
        6.0594,
        6.1755,
        6.2426,
        6.7018
    ],
    "gap": 0.31416998875040925,
    "homo": -0.268399990389311,
    "id": "AG7_00081",
    "ir": [
        0.024,
        0.0194,
        0.3865,
        0.1221,
        0.176,
        0.2923,
        6.5435,
        0.7418,
        0.9561,
        9.1132,
        0.0423,
        3.9385,
        7.8044,
        0.3952,
        5.0059,
        0.5007,
        0.8593,
        0.071,
        0.826,
        0.2594,
        4.683,
        0.0883,
        5.0362,
        0.1647,
        2.2731,
        6.5152,
        3.0867,
        12.2916,
        0.5048,
        72.2422,
        9.4267,
        14.7891,
        46.8346,
        34.7816,
        8.6428,
        25.4511,
        0.3809,
        47.1589,
        18.3503
    ],
    "lumo": 0.04576999836109823,
    "ma": [
        12.0,
        12.0,
        12.0,
        12.0,
        12.0,
        1.00783,
        1.00783,
        1.00783,
        1.00783,
        1.00783,
        1.00783,
        1.00783,
        1.00783,
        1.00783,
        1.00783
    ],
    "mr": [
        1.1114,
        1.0992,
        2.001,
        2.174,
        2.456,
        2.0256,
        2.8187,
        2.2054,
        1.1505,
        1.4974,
        1.6438,
        1.235,
        1.2951,
        2.4434,
        1.1745,
        1.4532,
        1.7171,
        1.7486,
        1.7145,
        1.7814,
        1.2884,
        1.2003,
        1.2515,
        1.5777,
        1.0438,
        1.056,
        1.0957,
        1.0403,
        1.3813,
        1.0349,
        1.0349,
        1.1016,
        1.1014,
        1.0997,
        1.1002,
        1.063,
        1.0803,
        1.088,
        1.1168
    ],
    "mu": 0.1191,
    "mu_x": 0.0,
    "mu_xx=": -0.3745,
    "mu_xxx=": 0.0,
    "mu_xxy=": 0.4077,
    "mu_xxz=": 0.0,
    "mu_xy=": 0.0,
    "mu_xyy=": 0.0,
    "mu_xyz=": -1.3454,
    "mu_xz=": -0.4608,
    "mu_xzz=": 0.0,
    "mu_y": -0.1191,
    "mu_yy=": -0.378,
    "mu_yyy=": -0.7957,
    "mu_yyz=": 0.0,
    "mu_yz=": 0.0,
    "mu_yzz=": 0.1181,
    "mu_z": 0.0,
    "mu_zz=": 0.7525,
    "mu_zzz=": 0.0,
    "na": 15,
    "ne": 40,
    "ne_down": 20,
    "ne_up": 20,
    "ni": 5,
    "oemga": [
        194.5527,
        213.4589,
        238.5546,
        294.0781,
        418.8455,
        435.5632,
        772.9645,
        786.4255,
        870.3397,
        885.4167,
        938.432,
        994.7056,
        1045.3073,
        1088.2857,
        1102.363,
        1130.845,
        1133.0212,
        1199.9879,
        1202.0527,
        1244.6952,
        1354.0674,
        1416.5723,
        1422.2408,
        1442.4535,
        1491.5337,
        1491.9734,
        1498.7682,
        1501.5519,
        1511.0562,
        3010.7864,
        3012.1766,
        3064.3937,
        3064.7501,
        3070.8118,
        3072.5206,
        3110.3955,
        3114.8696,
        3120.5795,
        3191.4093
    ],
    "oemga0": 3191.4093,
    "qa": [
        -0.29433,
        -0.04407,
        -0.247726,
        -0.04407,
        -0.29433,
        0.083947,
        0.0946,
        0.095485,
        0.093906,
        0.094325,
        0.094325,
        0.093906,
        0.095485,
        0.0946,
        0.083947
    ],
    "r2": 500.5578,
    "rn": [
        0.03,
        0.04,
        0.01,
        0.01,
        -0.03,
        0.0,
        0.0,
        -0.04,
        0.0,
        -0.01,
        -0.03,
        0.0,
        -0.03,
        0.04,
        -0.01,
        -0.12,
        -0.28,
        -0.1,
        0.25,
        0.08,
        0.36,
        0.0,
        0.39,
        -0.21,
        0.02,
        -0.03,
        0.0,
        0.0,
        -0.04,
        0.0,
        0.0,
        -0.04,
        0.0,
        -0.02,
        -0.03,
        0.0,
        0.0,
        0.39,
        0.21,
        -0.25,
        0.08,
        -0.36,
        0.12,
        -0.28,
        0.1,
        -0.01,
        0.0,
        -0.04,
        0.0,
        -0.02,
        0.02,
        0.02,
        0.0,
        0.06,
        0.0,
        0.02,
        0.02,
        -0.01,
        0.0,
        -0.04,
        -0.22,
        -0.33,
        -0.16,
        0.15,
        0.03,
        0.3,
        0.02,
        0.3,
        -0.32,
        0.03,
        -0.04,
        0.02,
        0.02,
        0.02,
        0.08,
        0.02,
        -0.02,
        0.08,
        0.03,
        0.04,
        0.02,
        0.02,
        -0.3,
        -0.32,
        0.15,
        -0.03,
        0.3,
        -0.22,
        0.33,
        -0.16,
        0.08,
        0.14,
        -0.01,
        0.0,
        -0.11,
        0.01,
        0.0,
        -0.12,
        0.0,
        0.0,
        -0.11,
        -0.01,
        -0.08,
        0.14,
        0.01,
        0.12,
        0.44,
        0.08,
        0.23,
        0.14,
        -0.29,
        -0.03,
        0.1,
        0.17,
        0.03,
        -0.16,
        0.0,
        0.06,
        -0.12,
        0.05,
        -0.06,
        -0.12,
        -0.05,
        -0.03,
        -0.16,
        0.0,
        0.03,
        0.1,
        -0.17,
        -0.23,
        0.14,
        0.29,
        -0.12,
        0.44,
        -0.08,
        -0.06,
        0.0,
        -0.11,
        0.07,
        0.09,
        0.16,
        -0.01,
        0.0,
        -0.02,
        0.07,
        -0.09,
        0.16,
        -0.06,
        0.0,
        -0.11,
        -0.23,
        0.11,
        -0.1,
        -0.2,
        -0.02,
        -0.28,
        0.13,
        -0.18,
        -0.22,
        0.21,
        0.23,
        0.22,
        -0.06,
        -0.03,
        -0.08,
        -0.06,
        0.03,
        -0.08,
        0.21,
        -0.23,
        0.22,
        0.13,
        0.18,
        -0.22,
        -0.2,
        0.02,
        -0.28,
        -0.23,
        -0.11,
        -0.1,
        0.19,
        -0.05,
        0.03,
        0.11,
        0.04,
        -0.11,
        0.0,
        0.03,
        0.0,
        -0.11,
        0.04,
        0.11,
        -0.19,
        -0.05,
        -0.03,
        0.41,
        -0.07,
        0.05,
        0.14,
        -0.05,
        0.09,
        0.09,
        -0.08,
        0.19,
        0.21,
        0.17,
        -0.06,
        -0.26,
        0.03,
        -0.19,
        0.26,
        0.03,
        0.19,
        -0.21,
        0.17,
        0.06,
        -0.09,
        -0.08,
        -0.19,
        -0.14,
        -0.05,
        -0.09,
        -0.41,
        -0.07,
        -0.05,
        -0.06,
        0.09,
        -0.01,
        -0.07,
        -0.07,
        0.05,
        0.21,
        0.0,
        -0.05,
        -0.07,
        0.07,
        0.05,
        -0.06,
        -0.09,
        -0.01,
        -0.14,
        0.24,
        0.03,
        0.14,
        0.1,
        -0.14,
        -0.12,
        0.18,
        0.01,
        -0.07,
        -0.01,
        0.06,
        0.4,
        -0.29,
        -0.15,
        0.4,
        0.29,
        -0.15,
        -0.07,
        0.01,
        0.06,
        -0.12,
        -0.18,
        0.01,
        0.14,
        -0.1,
        -0.14,
        -0.14,
        -0.24,
        0.03,
        -0.11,
        0.07,
        0.02,
        0.02,
        0.17,
        -0.11,
        0.2,
        0.0,
        0.1,
        0.02,
        -0.17,
        -0.11,
        -0.11,
        -0.07,
        0.02,
        0.09,
        -0.09,
        0.0,
        -0.37,
        0.06,
        0.19,
        -0.11,
        -0.04,
        0.11,
        0.09,
        0.16,
        -0.1,
        0.16,
        0.24,
        0.27,
        0.16,
        -0.24,
        0.27,
        0.09,
        -0.16,
        -0.1,
        -0.11,
        0.04,
        0.11,
        -0.37,
        -0.06,
        0.19,
        0.09,
        0.09,
        0.0,
        0.14,
        -0.02,
        -0.01,
        0.06,
        0.08,
        0.16,
        0.0,
        -0.06,
        0.0,
        -0.06,
        0.08,
        -0.16,
        -0.14,
        -0.02,
        0.01,
        -0.1,
        -0.05,
        -0.05,
        -0.04,
        -0.04,
        -0.09,
        0.39,
        -0.18,
        -0.24,
        -0.05,
        -0.1,
        0.09,
        0.3,
        -0.02,
        0.25,
        -0.3,
        -0.02,
        -0.25,
        0.05,
        -0.1,
        -0.09,
        -0.39,
        -0.18,
        0.24,
        0.04,
        -0.04,
        0.09,
        0.1,
        -0.05,
        0.05,
        -0.02,
        -0.03,
        0.0,
        -0.01,
        -0.05,
        0.0,
        0.03,
        0.0,
        -0.07,
        -0.01,
        0.05,
        0.0,
        -0.02,
        0.03,
        0.0,
        0.0,
        0.11,
        0.04,
        0.23,
        -0.01,
        -0.06,
        -0.15,
        0.12,
        0.06,
        0.15,
        0.34,
        0.13,
        -0.08,
        0.43,
        0.19,
        -0.08,
        -0.43,
        0.19,
        0.15,
        -0.34,
        0.13,
        -0.15,
        -0.12,
        0.06,
        0.23,
        0.01,
        -0.06,
        0.0,
        -0.11,
        0.04,
        0.04,
        -0.02,
        -0.05,
        -0.06,
        -0.03,
        -0.04,
        0.0,
        0.15,
        0.0,
        0.06,
        -0.03,
        0.04,
        -0.04,
        -0.02,
        0.05,
        0.26,
        -0.11,
        -0.05,
        0.02,
        -0.01,
        0.09,
        -0.08,
        0.0,
        0.1,
        -0.01,
        -0.33,
        -0.11,
        0.39,
        0.14,
        0.28,
        -0.39,
        0.14,
        -0.28,
        0.01,
        -0.33,
        0.11,
        0.08,
        0.0,
        -0.1,
        -0.02,
        -0.01,
        -0.09,
        -0.26,
        -0.11,
        0.05,
        0.06,
        -0.08,
        0.02,
        -0.06,
        -0.05,
        0.02,
        0.0,
        0.16,
        0.0,
        0.06,
        -0.05,
        -0.02,
        -0.06,
        -0.08,
        -0.02,
        -0.25,
        0.18,
        0.05,
        0.38,
        -0.05,
        -0.25,
        0.07,
        0.11,
        -0.15,
        -0.23,
        0.13,
        0.04,
        -0.14,
        0.16,
        -0.11,
        0.14,
        0.16,
        0.11,
        0.23,
        0.13,
        -0.04,
        -0.07,
        0.11,
        0.15,
        -0.38,
        -0.05,
        0.25,
        0.25,
        0.18,
        -0.05,
        0.0,
        0.01,
        0.08,
        0.03,
        0.0,
        -0.03,
        0.03,
        0.0,
        -0.05,
        0.03,
        0.0,
        -0.03,
        0.0,
        -0.01,
        0.08,
        -0.41,
        0.1,
        0.05,
        -0.04,
        -0.01,
        -0.17,
        0.24,
        -0.04,
        -0.22,
        -0.32,
        -0.08,
        -0.11,
        -0.03,
        0.22,
        0.08,
        -0.03,
        -0.22,
        0.08,
        -0.32,
        0.08,
        -0.11,
        0.24,
        0.04,
        -0.22,
        -0.04,
        0.01,
        -0.17,
        -0.41,
        -0.1,
        0.05,
        -0.06,
        0.0,
        0.01,
        0.06,
        -0.03,
        0.0,
        0.1,
        0.0,
        0.04,
        0.06,
        0.03,
        0.0,
        -0.06,
        0.0,
        0.01,
        -0.03,
        0.05,
        0.03,
        0.01,
        0.01,
        0.03,
        -0.14,
        0.07,
        0.07,
        0.05,
        -0.19,
        -0.04,
        -0.52,
        0.06,
        -0.38,
        -0.52,
        -0.06,
        -0.38,
        0.05,
        0.19,
        -0.04,
        -0.14,
        -0.07,
        0.07,
        0.01,
        -0.01,
        0.03,
        -0.03,
        -0.05,
        0.03,
        0.11,
        -0.05,
        -0.02,
        -0.15,
        0.1,
        -0.02,
        0.12,
        0.0,
        0.16,
        -0.15,
        -0.1,
        -0.02,
        0.11,
        0.05,
        -0.02,
        -0.01,
        0.04,
        -0.01,
        0.19,
        -0.05,
        -0.14,
        0.13,
        0.01,
        -0.11,
        -0.25,
        0.38,
        0.03,
        -0.29,
        -0.09,
        -0.21,
        -0.29,
        0.09,
        -0.21,
        -0.25,
        -0.38,
        0.03,
        0.13,
        -0.01,
        -0.11,
        0.19,
        0.05,
        -0.14,
        -0.01,
        -0.04,
        -0.01,
        -0.03,
        -0.06,
        -0.03,
        0.02,
        0.03,
        0.03,
        0.0,
        -0.04,
        0.0,
        -0.02,
        0.03,
        -0.03,
        0.03,
        -0.06,
        0.03,
        0.09,
        0.09,
        0.03,
        0.26,
        -0.02,
        -0.02,
        -0.23,
        0.14,
        0.1,
        0.21,
        0.38,
        0.15,
        0.26,
        -0.03,
        0.2,
        -0.26,
        -0.03,
        -0.2,
        -0.21,
        0.38,
        -0.15,
        0.23,
        0.14,
        -0.1,
        -0.26,
        -0.02,
        0.02,
        -0.09,
        0.09,
        -0.03,
        -0.03,
        -0.06,
        -0.03,
        0.05,
        0.1,
        0.04,
        0.0,
        -0.05,
        0.0,
        -0.05,
        0.1,
        -0.04,
        0.03,
        -0.06,
        0.03,
        0.11,
        0.12,
        0.04,
        0.27,
        -0.02,
        0.0,
        -0.21,
        0.15,
        0.08,
        -0.23,
        -0.44,
        -0.15,
        -0.15,
        -0.01,
        -0.09,
        0.15,
        -0.01,
        0.09,
        0.23,
        -0.44,
        0.15,
        0.21,
        0.15,
        -0.08,
        -0.27,
        -0.02,
        0.0,
        -0.11,
        0.12,
        -0.04,
        0.04,
        0.1,
        0.0,
        -0.06,
        -0.12,
        0.0,
        0.05,
        0.0,
        -0.02,
        -0.06,
        0.12,
        0.0,
        0.04,
        -0.1,
        0.0,
        0.05,
        -0.22,
        -0.08,
        -0.4,
        0.05,
        0.1,
        0.27,
        -0.25,
        -0.05,
        0.12,
        0.18,
        0.12,
        -0.15,
        0.13,
        -0.06,
        -0.15,
        -0.13,
        -0.06,
        0.12,
        -0.18,
        0.12,
        0.27,
        0.25,
        -0.05,
        -0.4,
        -0.05,
        0.1,
        0.05,
        0.22,
        -0.08,
        -0.04,
        -0.02,
        0.1,
        0.12,
        0.0,
        -0.08,
        0.0,
        0.05,
        0.0,
        -0.12,
        0.0,
        0.08,
        0.04,
        -0.02,
        -0.1,
        -0.36,
        0.14,
        0.1,
        0.03,
        -0.02,
        -0.13,
        0.03,
        0.09,
        -0.09,
        0.35,
        -0.27,
        -0.1,
        0.18,
        0.07,
        0.15,
        -0.18,
        0.07,
        -0.15,
        -0.35,
        -0.27,
        0.1,
        -0.03,
        0.09,
        0.09,
        -0.03,
        -0.02,
        0.13,
        0.36,
        0.14,
        -0.1,
        -0.03,
        -0.01,
        0.07,
        0.06,
        -0.05,
        -0.11,
        -0.07,
        0.0,
        0.11,
        0.06,
        0.05,
        -0.11,
        -0.03,
        0.01,
        0.07,
        -0.24,
        0.07,
        0.06,
        -0.01,
        -0.01,
        -0.11,
        0.03,
        0.05,
        -0.08,
        0.33,
        0.38,
        0.05,
        0.05,
        -0.34,
        -0.08,
        0.05,
        0.34,
        -0.08,
        0.33,
        -0.38,
        0.05,
        0.03,
        -0.05,
        -0.08,
        -0.01,
        0.01,
        -0.11,
        -0.24,
        -0.07,
        0.06,
        -0.02,
        0.01,
        -0.02,
        0.04,
        -0.06,
        0.15,
        0.0,
        0.11,
        0.0,
        -0.04,
        -0.06,
        -0.15,
        0.02,
        0.01,
        0.02,
        0.1,
        -0.03,
        -0.01,
        0.0,
        0.02,
        0.11,
        -0.07,
        -0.04,
        0.1,
        0.47,
        -0.17,
        0.21,
        -0.26,
        0.19,
        -0.14,
        0.26,
        0.19,
        0.14,
        -0.47,
        -0.17,
        -0.21,
        0.07,
        -0.04,
        -0.1,
        0.0,
        0.02,
        -0.11,
        -0.1,
        -0.03,
        0.01,
        0.01,
        -0.02,
        0.05,
        -0.08,
        0.05,
        -0.01,
        0.02,
        0.0,
        -0.03,
        -0.08,
        -0.05,
        -0.01,
        0.01,
        0.02,
        0.05,
        -0.02,
        0.0,
        0.04,
        0.08,
        -0.02,
        -0.14,
        0.14,
        0.01,
        -0.15,
        0.55,
        -0.34,
        0.01,
        0.0,
        0.07,
        0.0,
        0.0,
        -0.07,
        0.0,
        0.55,
        0.34,
        0.01,
        0.14,
        -0.01,
        -0.15,
        0.08,
        0.02,
        -0.14,
        -0.02,
        0.0,
        0.04,
        -0.07,
        0.02,
        0.04,
        -0.04,
        0.02,
        -0.01,
        0.0,
        0.01,
        0.0,
        0.04,
        0.02,
        0.01,
        0.07,
        0.02,
        -0.04,
        0.3,
        -0.17,
        0.02,
        0.34,
        0.04,
        -0.2,
        0.23,
        -0.15,
        -0.23,
        0.17,
        -0.06,
        0.0,
        0.05,
        -0.19,
        -0.11,
        -0.05,
        -0.19,
        0.11,
        -0.17,
        -0.06,
        0.0,
        -0.23,
        -0.15,
        0.23,
        -0.34,
        0.04,
        0.2,
        -0.3,
        -0.17,
        -0.02,
        0.09,
        -0.03,
        -0.02,
        -0.02,
        0.01,
        0.0,
        0.0,
        0.0,
        -0.01,
        -0.02,
        -0.01,
        0.0,
        0.09,
        0.03,
        -0.02,
        -0.37,
        0.17,
        -0.02,
        -0.38,
        -0.06,
        0.11,
        -0.23,
        0.22,
        0.21,
        0.09,
        -0.05,
        0.01,
        0.02,
        0.02,
        0.01,
        0.02,
        -0.02,
        0.01,
        0.09,
        0.05,
        0.01,
        -0.23,
        -0.22,
        0.21,
        -0.38,
        0.06,
        0.11,
        -0.37,
        -0.17,
        -0.02,
        0.07,
        -0.04,
        0.0,
        -0.12,
        0.06,
        0.0,
        0.0,
        0.0,
        0.0,
        0.12,
        0.06,
        0.0,
        -0.07,
        -0.04,
        0.0,
        -0.18,
        0.04,
        -0.01,
        -0.18,
        -0.06,
        -0.09,
        -0.11,
        0.2,
        0.06,
        0.37,
        -0.15,
        0.04,
        0.04,
        -0.35,
        -0.23,
        -0.04,
        -0.35,
        0.23,
        -0.37,
        -0.15,
        -0.04,
        0.11,
        0.2,
        -0.06,
        0.18,
        -0.06,
        0.09,
        0.18,
        0.04,
        0.01,
        -0.01,
        -0.03,
        -0.02,
        -0.01,
        -0.01,
        0.0,
        0.0,
        0.0,
        0.0,
        -0.01,
        0.01,
        0.0,
        -0.01,
        0.03,
        -0.02,
        0.16,
        0.45,
        0.15,
        -0.09,
        -0.01,
        0.37,
        0.16,
        0.03,
        -0.27,
        0.01,
        0.01,
        0.01,
        0.0,
        0.0,
        0.0,
        0.0,
        0.0,
        0.0,
        0.01,
        -0.01,
        0.01,
        0.16,
        -0.03,
        -0.27,
        -0.09,
        0.01,
        0.37,
        0.16,
        -0.45,
        0.15,
        -0.01,
        -0.04,
        0.0,
        -0.02,
        -0.01,
        -0.01,
        0.0,
        -0.01,
        0.0,
        0.02,
        -0.01,
        0.01,
        0.01,
        -0.04,
        0.0,
        0.24,
        0.41,
        0.15,
        -0.15,
        -0.02,
        0.26,
        0.15,
        0.13,
        -0.34,
        0.05,
        0.0,
        0.01,
        -0.03,
        0.05,
        0.02,
        0.03,
        0.05,
        -0.02,
        -0.05,
        0.0,
        -0.01,
        -0.15,
        0.13,
        0.34,
        0.15,
        -0.02,
        -0.26,
        -0.24,
        0.41,
        -0.15,
        0.01,
        -0.01,
        0.03,
        -0.03,
        0.01,
        0.0,
        0.0,
        -0.06,
        0.0,
        0.03,
        0.01,
        0.0,
        -0.01,
        -0.01,
        -0.03,
        0.18,
        -0.2,
        -0.01,
        -0.18,
        -0.04,
        -0.36,
        -0.07,
        0.29,
        -0.11,
        0.05,
        -0.01,
        0.01,
        -0.16,
        0.32,
        0.18,
        0.16,
        0.32,
        -0.18,
        -0.05,
        -0.01,
        -0.01,
        0.07,
        0.29,
        0.11,
        0.18,
        -0.04,
        0.36,
        -0.18,
        -0.2,
        0.01,
        0.0,
        0.02,
        -0.03,
        -0.01,
        0.01,
        -0.01,
        0.0,
        0.0,
        0.0,
        -0.01,
        -0.01,
        -0.01,
        0.0,
        -0.02,
        -0.03,
        -0.3,
        0.08,
        -0.04,
        0.29,
        0.05,
        0.3,
        0.06,
        -0.4,
        0.23,
        0.07,
        -0.03,
        -0.01,
        0.0,
        0.0,
        0.0,
        0.0,
        0.0,
        0.0,
        0.07,
        0.03,
        -0.01,
        0.06,
        0.4,
        0.23,
        0.29,
        -0.05,
        0.3,
        -0.3,
        -0.08,
        -0.04,
        0.01,
        0.0,
        -0.01,
        -0.09,
        0.04,
        -0.03,
        0.0,
        -0.11,
        0.0,
        0.09,
        0.04,
        0.03,
        -0.01,
        0.0,
        0.01,
        -0.2,
        0.07,
        -0.01,
        0.24,
        0.03,
        0.18,
        0.1,
        -0.28,
        0.1,
        0.21,
        -0.07,
        -0.01,
        -0.19,
        0.35,
        0.21,
        0.19,
        0.35,
        -0.21,
        -0.21,
        -0.07,
        0.01,
        -0.1,
        -0.28,
        -0.1,
        -0.24,
        0.03,
        -0.18,
        0.2,
        0.07,
        0.01,
        -0.03,
        0.01,
        0.01,
        0.0,
        0.0,
        0.0,
        0.0,
        0.0,
        0.0,
        0.0,
        0.0,
        0.0,
        -0.03,
        -0.01,
        0.01,
        0.04,
        0.11,
        -0.36,
        0.03,
        -0.43,
        0.02,
        0.3,
        0.18,
        0.23,
        0.0,
        0.0,
        0.0,
        0.0,
        0.0,
        0.0,
        0.0,
        0.0,
        0.0,
        0.0,
        0.0,
        0.0,
        0.3,
        -0.18,
        0.23,
        0.03,
        0.43,
        0.02,
        0.04,
        -0.11,
        -0.36,
        0.03,
        -0.01,
        -0.01,
        0.0,
        0.0,
        0.0,
        0.0,
        0.0,
        0.0,
        0.0,
        0.0,
        0.0,
        -0.03,
        -0.01,
        0.01,
        -0.04,
        -0.11,
        0.36,
        -0.03,
        0.42,
        -0.02,
        -0.31,
        -0.18,
        -0.23,
        0.0,
        -0.01,
        0.02,
        0.0,
        0.0,
        -0.01,
        0.0,
        0.0,
        0.01,
        0.0,
        -0.01,
        -0.02,
        0.31,
        -0.18,
        0.23,
        0.03,
        0.42,
        0.02,
        0.04,
        -0.11,
        -0.36,
        -0.03,
        -0.06,
        -0.02,
        0.0,
        0.0,
        0.0,
        0.0,
        0.0,
        0.0,
        0.0,
        0.0,
        0.0,
        -0.03,
        0.06,
        -0.02,
        0.0,
        -0.01,
        -0.03,
        -0.05,
        0.5,
        -0.03,
        0.36,
        0.2,
        0.27,
        0.0,
        0.0,
        0.01,
        0.0,
        0.0,
        0.0,
        0.0,
        0.0,
        0.0,
        0.0,
        0.0,
        0.01,
        0.36,
        -0.2,
        0.27,
        -0.05,
        -0.5,
        -0.03,
        0.0,
        0.01,
        -0.03,
        -0.03,
        -0.06,
        -0.02,
        0.0,
        0.0,
        0.0,
        0.0,
        0.0,
        0.0,
        0.0,
        0.0,
        0.0,
        0.03,
        -0.06,
        0.02,
        -0.01,
        -0.02,
        0.01,
        -0.05,
        0.48,
        -0.03,
        0.38,
        0.2,
        0.27,
        0.0,
        0.0,
        0.0,
        0.0,
        0.0,
        0.0,
        0.0,
        0.0,
        0.0,
        0.0,
        0.0,
        0.0,
        -0.38,
        0.2,
        -0.27,
        0.05,
        0.48,
        0.03,
        0.01,
        -0.02,
        -0.01,
        -0.01,
        0.02,
        -0.06,
        0.0,
        0.0,
        0.01,
        0.0,
        0.0,
        0.0,
        0.0,
        0.0,
        0.01,
        -0.01,
        -0.02,
        -0.06,
        -0.07,
        -0.16,
        0.55,
        0.02,
        -0.23,
        0.0,
        0.2,
        0.12,
        0.14,
        0.03,
        0.04,
        -0.16,
        0.0,
        0.0,
        0.0,
        0.0,
        0.0,
        0.0,
        0.03,
        -0.04,
        -0.16,
        0.2,
        -0.12,
        0.14,
        0.02,
        0.23,
        0.0,
        -0.07,
        0.16,
        0.55,
        -0.01,
        0.03,
        -0.06,
        0.0,
        0.0,
        0.01,
        0.0,
        0.0,
        0.0,
        0.0,
        0.0,
        -0.01,
        0.01,
        0.03,
        0.06,
        -0.07,
        -0.16,
        0.56,
        0.02,
        -0.27,
        0.0,
        0.18,
        0.11,
        0.12,
        0.02,
        0.03,
        -0.13,
        0.02,
        0.01,
        -0.02,
        -0.02,
        0.01,
        0.02,
        -0.02,
        0.03,
        0.13,
        -0.18,
        0.11,
        -0.12,
        -0.02,
        -0.27,
        0.0,
        0.07,
        -0.16,
        -0.56,
        0.0,
        0.0,
        -0.01,
        0.01,
        0.01,
        -0.03,
        0.0,
        0.05,
        0.0,
        -0.01,
        0.01,
        0.03,
        0.0,
        0.0,
        0.01,
        -0.01,
        -0.02,
        0.08,
        0.0,
        -0.04,
        0.0,
        0.03,
        0.02,
        0.02,
        -0.07,
        -0.1,
        0.38,
        -0.29,
        -0.3,
        0.39,
        0.29,
        -0.3,
        -0.39,
        0.07,
        -0.1,
        -0.38,
        -0.03,
        0.02,
        -0.02,
        0.0,
        -0.04,
        0.0,
        0.01,
        -0.02,
        -0.08,
        0.0,
        0.0,
        -0.01,
        0.01,
        0.01,
        -0.05,
        0.0,
        -0.04,
        0.0,
        -0.01,
        0.01,
        0.05,
        0.0,
        0.0,
        0.01,
        -0.01,
        -0.02,
        0.06,
        0.01,
        -0.05,
        0.0,
        0.04,
        0.02,
        0.02,
        -0.1,
        -0.14,
        0.53,
        0.22,
        0.22,
        -0.28,
        -0.22,
        0.22,
        0.28,
        0.1,
        -0.14,
        -0.53,
        -0.04,
        0.02,
        -0.02,
        -0.01,
        -0.05,
        0.0,
        0.01,
        -0.02,
        -0.06,
        0.0,
        0.01,
        -0.01,
        0.01,
        0.01,
        -0.05,
        -0.01,
        0.0,
        0.01,
        0.01,
        -0.01,
        -0.05,
        0.0,
        -0.01,
        -0.01,
        -0.02,
        -0.04,
        0.14,
        0.01,
        -0.06,
        0.0,
        0.05,
        0.03,
        0.03,
        -0.12,
        -0.17,
        0.65,
        0.04,
        0.04,
        -0.06,
        0.04,
        -0.04,
        -0.06,
        -0.12,
        0.17,
        0.65,
        0.05,
        -0.03,
        0.03,
        0.01,
        0.06,
        0.0,
        -0.02,
        0.04,
        0.14,
        0.0,
        0.0,
        0.0,
        0.0,
        0.0,
        0.01,
        -0.06,
        0.0,
        0.08,
        0.0,
        0.0,
        0.01,
        0.0,
        0.0,
        0.0,
        0.0,
        0.0,
        -0.02,
        0.0,
        0.0,
        0.0,
        0.0,
        0.0,
        0.0,
        0.01,
        0.02,
        -0.08,
        0.35,
        0.38,
        -0.47,
        0.35,
        -0.38,
        -0.47,
        0.01,
        -0.02,
        -0.08,
        0.0,
        0.0,
        0.0,
        0.0,
        0.0,
        0.0,
        0.0,
        0.0,
        -0.02
    ],
    "smi": "CC1CC1C",
    "symbols": [
        "C",
        "C",
        "C",
        "C",
        "C",
        "H",
        "H",
        "H",
        "H",
        "H",
        "H",
        "H",
        "H",
        "H",
        "H"
    ],
    "zpe": 0.137038,
    "zs": [
        6,
        6,
        6,
        6,
        6,
        1,
        1,
        1,
        1,
        1,
        1,
        1,
        1,
        1,
        1
    ]
}