{
    "A": 5.18037,
    "B": 3.43471,
    "C": 3.26805,
    "Cv": "21.737",
    "G": -319.302034,
    "H": -319.266907,
    "P": 1.0,
    "S": 0.00011781653530098469,
    "T": 298.15,
    "U": -319.267851,
    "U0": -319.273372,
    "alpha": 42.74866666666666,
    "alpha_xx": 71.384,
    "alpha_xy": -2.908,
    "alpha_xz": 61.542,
    "alpha_yy": 3.874,
    "alpha_yz": 0.69,
    "alpha_zz": 52.988,
    "bo": [],
    "coords": [
        -1.477413,
        -0.285042,
        -0.312084,
        -0.724885,
        0.600656,
        0.500037,
        0.066438,
        -0.186049,
        1.593275,
        0.336706,
        -0.603874,
        0.386671,
        -0.728881,
        -1.424562,
        -0.298901,
        -1.007855,
        -2.323799,
        0.074554,
        1.098381,
        0.294014,
        -0.597951,
        0.288069,
        1.507329,
        -0.247092,
        -2.272426,
        -0.071556,
        -1.018015,
        2.043118,
        0.3714,
        -0.23447,
        -0.097065,
        2.001136,
        -1.13733,
        0.778113,
        2.221045,
        0.411305
    ],
    "e ne": -1333.795434473,
    "e_disp": -0.00621593809995602,
    "e_k": 317.3925735731,
    "e_nn": 295.140665826,
    "et": [
        -319.362664956
    ],
    "fc": [
        0.0516,
        0.118,
        0.232,
        0.9548,
        0.757,
        0.9808,
        0.8102,
        1.3817,
        1.3726,
        2.741,
        2.1347,
        0.9187,
        1.6341,
        1.1522,
        1.5552,
        0.9738,
        1.1071,
        1.1311,
        1.2151,
        1.259,
        2.2965,
        1.5999,
        3.4481,
        5.5625,
        1.4639,
        5.821,
        6.3709,
        6.411,
        7.7095,
        7.8332
    ],
    "id": "AG7_41115",
    "ir": [
        109.8062,
        51.9731,
        48.6379,
        7.2832,
        34.9986,
        40.2213,
        90.3487,
        0.5196,
        85.9313,
        10.6174,
        17.7232,
        41.0165,
        46.5832,
        1.0644,
        34.4357,
        34.4304,
        13.3141,
        4.9006,
        8.45,
        8.126,
        28.545,
        12.6818,
        7.9651,
        86.6579,
        0.3474,
        53.2182,
        16.902,
        7.4622,
        7.0648,
        23.4161
    ],
    "m_a": [
        12.0,
        12.0,
        14.00307,
        12.0,
        14.00307,
        1.00783,
        14.00307,
        12.0,
        1.00783,
        1.00783,
        1.00783,
        1.00783
    ],
    "mr": [
        1.8192,
        1.9047,
        2.7784,
        6.8937,
        4.4751,
        5.4634,
        2.9868,
        4.7315,
        4.2918,
        7.6619,
        5.2822,
        2.0225,
        3.3858,
        2.0734,
        2.6961,
        1.4609,
        1.4138,
        1.3717,
        1.4083,
        1.3141,
        2.1857,
        1.4772,
        2.9864,
        4.7107,
        1.096,
        1.0547,
        1.1133,
        1.0938,
        1.0745,
        1.0771
    ],
    "mu": 2.67615572230018,
    "mu_x": -0.8173,
    "mu_xx=": 7.2646,
    "mu_xxx=": -8.6372,
    "mu_xxy=": -3.2267,
    "mu_xxz=": -3.7105,
    "mu_xy=": -0.9249,
    "mu_xyy=": -1.9771,
    "mu_xyz=": 0.03,
    "mu_xz=": 1.1421,
    "mu_xzz=": 0.7875,
    "mu_y": 2.0446,
    "mu_yy=": 0.839,
    "mu_yyy=": 8.1509,
    "mu_yyz=": -8.5704,
    "mu_yz=": 5.6372,
    "mu_yzz=": 1.0615,
    "mu_z": -1.521,
    "mu_zz=": -8.1036,
    "mu_zzz=": -3.578,
    "na": 12,
    "ne": 50,
    "ne_down": 25,
    "ne_up": 25,
    "ni": 7,
    "oemga": [
        219.4589,
        324.2937,
        376.4285,
        484.8446,
        535.8081,
        552.0011,
        678.5299,
        704.0171,
        736.748,
        779.2232,
        828.196,
        878.0683,
        905.0722,
        971.1476,
        989.4522,
        1063.6634,
        1152.8758,
        1183.0523,
        1210.1596,
        1275.1954,
        1335.4158,
        1355.8316,
        1399.8745,
        1415.6892,
        1505.6594,
        3060.6525,
        3116.5688,
        3154.0336,
        3489.6723,
        3513.2731
    ],
    "oemga0": 3513.2731,
    "qa": [
        -0.001195,
        0.025529,
        -0.342834,
        0.150382,
        -0.117326,
        0.14685,
        -0.219579,
        -0.082463,
        0.127895,
        0.121281,
        0.08852,
        0.10294
    ],
    "r2": 496.0496,
    "rn": [
        0.1,
        -0.01,
        -0.06,
        0.02,
        -0.03,
        -0.01,
        -0.01,
        0.06,
        -0.01,
        -0.08,
        0.02,
        -0.03,
        -0.08,
        -0.1,
        -0.01,
        0.06,
        -0.3,
        0.67,
        -0.02,
        0.11,
        0.0,
        0.05,
        -0.03,
        0.09,
        0.39,
        0.04,
        -0.37,
        -0.05,
        0.1,
        -0.07,
        0.13,
        -0.02,
        0.18,
        -0.01,
        -0.16,
        0.07,
        -0.09,
        0.01,
        -0.06,
        -0.02,
        0.09,
        -0.04,
        0.06,
        0.03,
        0.04,
        0.05,
        -0.01,
        0.03,
        0.02,
        -0.03,
        0.03,
        -0.05,
        0.07,
        -0.32,
        -0.07,
        0.08,
        -0.05,
        0.06,
        -0.14,
        0.06,
        -0.34,
        -0.04,
        0.06,
        -0.07,
        0.13,
        -0.39,
        0.43,
        -0.18,
        0.19,
        -0.15,
        -0.47,
        0.15,
        0.14,
        -0.01,
        -0.12,
        0.0,
        -0.11,
        0.12,
        0.0,
        -0.02,
        0.11,
        -0.02,
        -0.1,
        0.07,
        0.11,
        0.02,
        -0.03,
        -0.06,
        0.3,
        -0.53,
        -0.15,
        0.12,
        -0.02,
        -0.08,
        0.04,
        -0.03,
        0.39,
        0.04,
        -0.28,
        -0.06,
        0.24,
        -0.31,
        -0.23,
        0.09,
        0.04,
        0.03,
        0.08,
        -0.16,
        0.08,
        0.2,
        -0.22,
        -0.05,
        0.25,
        -0.08,
        0.18,
        -0.44,
        -0.15,
        -0.06,
        -0.01,
        0.12,
        -0.05,
        0.0,
        0.15,
        -0.17,
        0.24,
        0.14,
        -0.04,
        -0.03,
        0.07,
        -0.08,
        0.07,
        0.08,
        0.17,
        0.21,
        -0.43,
        -0.03,
        -0.07,
        0.31,
        0.03,
        0.03,
        0.03,
        -0.13,
        0.05,
        0.15,
        -0.01,
        0.02,
        -0.04,
        -0.09,
        -0.17,
        0.0,
        0.33,
        0.19,
        -0.02,
        -0.05,
        -0.03,
        -0.11,
        -0.15,
        0.09,
        0.05,
        -0.29,
        0.33,
        -0.41,
        0.07,
        -0.09,
        -0.01,
        -0.12,
        -0.05,
        0.12,
        0.28,
        0.09,
        -0.15,
        0.02,
        -0.19,
        0.35,
        -0.13,
        -0.06,
        0.11,
        -0.15,
        -0.01,
        0.2,
        0.01,
        0.01,
        -0.08,
        0.09,
        -0.08,
        -0.23,
        -0.2,
        -0.01,
        0.08,
        -0.12,
        -0.21,
        0.0,
        -0.1,
        -0.02,
        0.26,
        -0.31,
        0.34,
        -0.46,
        0.26,
        0.15,
        -0.08,
        0.07,
        0.07,
        0.01,
        -0.15,
        -0.02,
        0.09,
        0.27,
        0.13,
        0.07,
        -0.03,
        0.14,
        0.16,
        0.08,
        0.15,
        0.07,
        -0.02,
        -0.01,
        -0.01,
        -0.01,
        0.01,
        0.17,
        -0.04,
        0.02,
        -0.08,
        -0.15,
        0.21,
        -0.01,
        0.1,
        -0.15,
        0.12,
        0.05,
        -0.1,
        -0.6,
        0.05,
        0.02,
        -0.08,
        0.03,
        -0.04,
        -0.05,
        0.03,
        -0.03,
        -0.32,
        -0.15,
        -0.24,
        0.5,
        0.07,
        -0.03,
        0.0,
        0.04,
        -0.1,
        -0.11,
        0.08,
        0.12,
        -0.12,
        -0.1,
        0.01,
        0.15,
        -0.12,
        0.07,
        -0.06,
        0.25,
        -0.04,
        -0.11,
        0.09,
        -0.02,
        0.22,
        0.16,
        -0.11,
        0.56,
        0.05,
        -0.07,
        -0.17,
        -0.23,
        -0.07,
        0.05,
        -0.22,
        0.05,
        0.06,
        0.22,
        0.07,
        -0.27,
        -0.32,
        -0.04,
        0.1,
        -0.18,
        -0.02,
        0.01,
        -0.02,
        0.06,
        0.19,
        -0.04,
        0.05,
        -0.13,
        0.05,
        -0.03,
        0.12,
        -0.15,
        -0.08,
        0.11,
        0.19,
        0.01,
        -0.12,
        0.27,
        -0.12,
        0.27,
        0.06,
        0.04,
        -0.26,
        -0.17,
        -0.02,
        0.04,
        0.23,
        0.11,
        0.01,
        0.1,
        -0.09,
        0.49,
        0.03,
        -0.01,
        0.26,
        -0.33,
        -0.23,
        0.13,
        0.05,
        0.1,
        0.06,
        0.09,
        -0.05,
        -0.32,
        0.01,
        0.14,
        -0.12,
        -0.16,
        -0.08,
        -0.22,
        0.34,
        -0.11,
        0.15,
        0.33,
        -0.08,
        -0.12,
        -0.25,
        -0.05,
        0.25,
        -0.06,
        0.04,
        0.12,
        -0.31,
        0.01,
        0.28,
        -0.24,
        0.02,
        0.01,
        -0.18,
        0.02,
        -0.04,
        -0.03,
        0.17,
        0.17,
        -0.06,
        0.05,
        0.03,
        -0.05,
        -0.25,
        -0.28,
        -0.05,
        -0.09,
        0.12,
        0.21,
        0.36,
        0.09,
        -0.01,
        -0.02,
        0.07,
        0.04,
        -0.15,
        -0.23,
        -0.05,
        -0.07,
        -0.06,
        0.0,
        0.04,
        0.08,
        0.44,
        0.16,
        -0.38,
        -0.1,
        -0.07,
        -0.32,
        -0.16,
        0.07,
        0.08,
        0.04,
        0.12,
        0.07,
        -0.09,
        0.05,
        0.13,
        -0.11,
        0.04,
        0.0,
        -0.01,
        0.0,
        -0.03,
        0.04,
        -0.09,
        -0.05,
        0.03,
        0.0,
        0.05,
        0.08,
        -0.11,
        -0.15,
        0.06,
        0.02,
        0.1,
        0.0,
        -0.04,
        -0.13,
        0.61,
        0.19,
        -0.47,
        0.15,
        0.17,
        -0.29,
        0.19,
        -0.09,
        -0.2,
        -0.15,
        -0.08,
        0.06,
        -0.08,
        0.17,
        -0.11,
        -0.13,
        -0.18,
        0.02,
        0.09,
        -0.04,
        0.08,
        -0.11,
        0.05,
        0.03,
        0.07,
        0.03,
        -0.01,
        0.16,
        -0.11,
        0.47,
        0.1,
        0.1,
        0.1,
        0.05,
        -0.13,
        -0.14,
        -0.53,
        0.08,
        0.16,
        0.0,
        0.06,
        -0.07,
        -0.26,
        -0.04,
        -0.06,
        0.24,
        0.08,
        -0.27,
        0.09,
        -0.07,
        -0.04,
        0.03,
        -0.04,
        -0.06,
        -0.02,
        0.0,
        0.01,
        0.07,
        0.07,
        0.01,
        -0.02,
        0.01,
        0.02,
        -0.03,
        0.03,
        0.02,
        0.01,
        0.06,
        0.12,
        -0.15,
        -0.01,
        -0.15,
        0.0,
        -0.07,
        0.25,
        0.12,
        0.1,
        0.47,
        0.34,
        -0.01,
        0.16,
        -0.42,
        -0.51,
        -0.11,
        0.05,
        -0.06,
        0.03,
        0.14,
        0.12,
        -0.05,
        0.02,
        0.01,
        -0.03,
        -0.07,
        0.1,
        0.07,
        -0.03,
        -0.02,
        -0.03,
        -0.03,
        -0.04,
        -0.18,
        0.1,
        0.03,
        0.06,
        -0.17,
        -0.19,
        0.0,
        0.02,
        -0.07,
        0.01,
        0.03,
        0.09,
        -0.57,
        -0.62,
        -0.1,
        0.0,
        0.0,
        0.28,
        0.07,
        0.07,
        -0.03,
        -0.02,
        -0.06,
        -0.04,
        0.03,
        0.01,
        -0.01,
        0.01,
        -0.1,
        0.06,
        0.01,
        0.02,
        -0.02,
        0.0,
        -0.02,
        0.08,
        0.07,
        0.05,
        -0.05,
        -0.02,
        0.0,
        0.09,
        -0.03,
        -0.04,
        -0.04,
        0.27,
        0.0,
        0.01,
        -0.49,
        0.34,
        -0.06,
        -0.27,
        -0.38,
        0.11,
        0.53,
        -0.04,
        0.03,
        0.01,
        0.08,
        -0.02,
        0.03,
        0.01,
        0.0,
        0.0,
        -0.06,
        0.01,
        -0.01,
        0.01,
        0.02,
        -0.01,
        0.02,
        -0.02,
        0.02,
        0.02,
        -0.1,
        0.02,
        -0.01,
        0.09,
        -0.03,
        -0.23,
        -0.05,
        -0.35,
        0.21,
        0.11,
        -0.36,
        0.04,
        0.29,
        0.64,
        -0.09,
        -0.27,
        -0.18,
        -0.06,
        -0.07,
        0.0,
        0.09,
        -0.04,
        0.01,
        -0.01,
        -0.02,
        0.02,
        0.02,
        0.0,
        -0.02,
        0.04,
        0.08,
        0.02,
        -0.01,
        0.21,
        0.24,
        -0.01,
        0.04,
        0.0,
        -0.04,
        -0.01,
        0.01,
        -0.35,
        -0.2,
        -0.68,
        -0.09,
        -0.05,
        0.12,
        0.1,
        -0.15,
        -0.33,
        -0.14,
        0.1,
        0.24,
        -0.01,
        -0.1,
        0.02,
        -0.1,
        0.03,
        -0.04,
        0.0,
        0.03,
        -0.04,
        0.0,
        0.03,
        0.03,
        0.07,
        -0.04,
        0.01,
        -0.33,
        0.78,
        0.35,
        0.01,
        -0.01,
        0.01,
        0.03,
        -0.01,
        -0.01,
        0.13,
        -0.07,
        -0.02,
        -0.02,
        -0.02,
        -0.06,
        -0.1,
        0.07,
        0.16,
        0.13,
        -0.06,
        -0.19,
        0.0,
        0.05,
        0.02,
        0.03,
        -0.02,
        0.0,
        0.0,
        -0.01,
        0.01,
        -0.03,
        0.03,
        -0.01,
        -0.01,
        -0.05,
        -0.02,
        -0.1,
        0.11,
        -0.02,
        0.02,
        -0.02,
        0.0,
        -0.07,
        0.04,
        0.1,
        -0.06,
        0.03,
        0.0,
        0.33,
        0.23,
        -0.1,
        0.29,
        -0.23,
        -0.52,
        0.23,
        -0.21,
        -0.52,
        -0.06,
        0.17,
        0.04,
        0.13,
        -0.07,
        0.05,
        -0.02,
        0.01,
        -0.04,
        0.05,
        0.0,
        0.03,
        -0.03,
        -0.15,
        -0.07,
        -0.33,
        0.41,
        0.06,
        -0.05,
        0.0,
        -0.01,
        0.02,
        -0.04,
        -0.05,
        0.0,
        0.22,
        0.08,
        0.34,
        0.26,
        0.23,
        -0.09,
        0.0,
        0.02,
        -0.23,
        0.17,
        0.48,
        -0.07,
        0.06,
        -0.02,
        0.09,
        -0.01,
        0.03,
        -0.01,
        -0.02,
        0.03,
        0.03,
        -0.03,
        -0.05,
        0.0,
        -0.05,
        -0.03,
        -0.1,
        0.15,
        0.07,
        0.06,
        0.03,
        0.02,
        -0.07,
        0.05,
        0.01,
        0.17,
        0.16,
        0.15,
        -0.7,
        -0.51,
        -0.21,
        0.11,
        0.01,
        0.01,
        -0.06,
        -0.12,
        -0.13,
        0.24,
        0.1,
        0.17,
        -0.13,
        0.05,
        -0.02,
        0.0,
        -0.04,
        0.11,
        0.04,
        0.01,
        -0.14,
        -0.08,
        -0.1,
        -0.06,
        -0.22,
        0.14,
        -0.2,
        0.01,
        0.02,
        0.01,
        0.02,
        0.0,
        -0.02,
        -0.63,
        -0.18,
        -0.39,
        -0.24,
        -0.17,
        -0.01,
        -0.17,
        0.05,
        0.05,
        -0.04,
        -0.07,
        0.0,
        -0.1,
        -0.08,
        -0.08,
        0.05,
        0.13,
        0.04,
        0.03,
        -0.13,
        0.28,
        -0.06,
        0.11,
        -0.39,
        0.03,
        0.01,
        0.03,
        -0.04,
        0.18,
        0.13,
        -0.03,
        -0.03,
        -0.01,
        0.03,
        -0.05,
        -0.01,
        0.42,
        0.09,
        0.31,
        0.42,
        0.3,
        0.12,
        -0.18,
        0.04,
        0.11,
        0.0,
        0.1,
        0.13,
        0.01,
        0.0,
        0.01,
        -0.01,
        0.0,
        0.0,
        0.0,
        0.0,
        0.01,
        0.01,
        0.0,
        -0.01,
        0.0,
        -0.01,
        0.0,
        -0.02,
        0.02,
        0.0,
        -0.01,
        0.0,
        0.0,
        -0.07,
        -0.05,
        -0.02,
        -0.02,
        -0.01,
        -0.02,
        -0.01,
        0.0,
        0.01,
        0.62,
        -0.05,
        0.34,
        0.3,
        0.63,
        -0.05,
        0.0,
        0.0,
        0.0,
        0.0,
        0.0,
        0.0,
        0.0,
        0.0,
        0.0,
        0.0,
        0.0,
        0.0,
        0.0,
        0.0,
        0.0,
        0.0,
        0.0,
        0.0,
        0.0,
        0.0,
        0.0,
        0.05,
        0.04,
        0.01,
        0.0,
        0.01,
        0.0,
        0.01,
        0.0,
        0.0,
        -0.12,
        -0.72,
        0.23,
        -0.48,
        0.26,
        -0.34,
        0.0,
        0.0,
        0.0,
        0.0,
        0.0,
        0.0,
        0.0,
        0.0,
        0.0,
        0.0,
        0.0,
        0.0,
        0.0,
        0.0,
        0.0,
        0.0,
        0.0,
        0.0,
        0.0,
        0.0,
        0.0,
        -0.04,
        0.07,
        -0.05,
        0.0,
        0.01,
        0.0,
        -0.02,
        0.01,
        0.0,
        -0.12,
        -0.6,
        0.19,
        0.58,
        -0.29,
        0.4,
        -0.02,
        0.08,
        -0.01,
        0.0,
        0.0,
        0.0,
        0.0,
        0.0,
        0.0,
        0.0,
        0.0,
        0.0,
        0.0,
        0.0,
        0.0,
        -0.01,
        0.0,
        0.0,
        0.0,
        0.0,
        0.0,
        0.0,
        0.0,
        0.0,
        0.26,
        -0.96,
        0.08,
        0.0,
        0.0,
        0.0,
        0.0,
        -0.02,
        0.0,
        0.0,
        0.0,
        0.0,
        0.0,
        0.0,
        0.0,
        0.0,
        0.0,
        0.0,
        0.0,
        0.0,
        0.0,
        0.0,
        0.0,
        0.0,
        0.0,
        0.0,
        0.0,
        -0.03,
        -0.01,
        0.0,
        0.04,
        -0.06,
        -0.01,
        0.0,
        0.0,
        0.0,
        0.0,
        0.0,
        0.0,
        -0.6,
        0.78,
        0.14,
        0.0,
        0.01,
        0.0,
        -0.01,
        0.01,
        -0.01,
        0.0,
        0.0,
        0.0,
        0.0,
        0.0,
        0.0,
        0.0,
        0.0,
        0.0,
        0.0,
        0.0,
        0.0,
        -0.06,
        -0.03,
        0.0,
        0.89,
        0.46,
        -0.04,
        0.0,
        0.0,
        0.0,
        0.0,
        0.0,
        0.0,
        0.0,
        -0.01,
        0.0,
        -0.02,
        0.02,
        0.0,
        0.0,
        0.0,
        0.0,
        0.0,
        0.0,
        0.0
    ],
    "smi": "",
    "symbols": [
        "C",
        "C",
        "N",
        "C",
        "N",
        "H",
        "N",
        "C",
        "H",
        "H",
        "H",
        "H"
    ],
    "zpe": 0.089293,
    "zs": [
        6,
        6,
        7,
        6,
        7,
        1,
        7,
        6,
        1,
        1,
        1,
        1
    ]
}